{
"meta":{"test_sets":[],"test_metrics":[],"learn_metrics":[{"best_value":"Min","name":"RMSE"}],"launch_mode":"Train","parameters":"","iteration_count":1000,"learn_sets":["learn"],"name":"experiment"},
"iterations":[
{"learn":[0.4838229914],"iteration":0,"passed_time":0.003496870139,"remaining_time":3.493373268},
{"learn":[0.4797447533],"iteration":1,"passed_time":0.00719819589,"remaining_time":3.591899749},
{"learn":[0.4763924149],"iteration":2,"passed_time":0.01086098049,"remaining_time":3.609465849},
{"learn":[0.4732096857],"iteration":3,"passed_time":0.01356898612,"remaining_time":3.378677544},
{"learn":[0.4705223615],"iteration":4,"passed_time":0.0159384546,"remaining_time":3.171752464},
{"learn":[0.4680407253],"iteration":5,"passed_time":0.01845279614,"remaining_time":3.057013227},
{"learn":[0.4658351918],"iteration":6,"passed_time":0.02149488066,"remaining_time":3.049202357},
{"learn":[0.4639461539],"iteration":7,"passed_time":0.02417905328,"remaining_time":2.998202607},
{"learn":[0.462197043],"iteration":8,"passed_time":0.02795758634,"remaining_time":3.078440896},
{"learn":[0.4605770412],"iteration":9,"passed_time":0.03201032408,"remaining_time":3.169022084},
{"learn":[0.45928869],"iteration":10,"passed_time":0.03523273954,"remaining_time":3.167743582},
{"learn":[0.4581007664],"iteration":11,"passed_time":0.03888673259,"remaining_time":3.201674316},
{"learn":[0.4570430648],"iteration":12,"passed_time":0.04197127488,"remaining_time":3.186588331},
{"learn":[0.4560921389],"iteration":13,"passed_time":0.04484419499,"remaining_time":3.15831259},
{"learn":[0.455237422],"iteration":14,"passed_time":0.04780590558,"remaining_time":3.139254466},
{"learn":[0.4544558479],"iteration":15,"passed_time":0.05114631946,"remaining_time":3.145498647},
{"learn":[0.4537543579],"iteration":16,"passed_time":0.05407557216,"remaining_time":3.126840437},
{"learn":[0.453086997],"iteration":17,"passed_time":0.05763539979,"remaining_time":3.144331255},
{"learn":[0.4525721199],"iteration":18,"passed_time":0.06164517977,"remaining_time":3.182837966},
{"learn":[0.4520389116],"iteration":19,"passed_time":0.06419993744,"remaining_time":3.145796935},
{"learn":[0.4515507807],"iteration":20,"passed_time":0.06774305697,"remaining_time":3.158116799},
{"learn":[0.4510891226],"iteration":21,"passed_time":0.07042277131,"remaining_time":3.130612288},
{"learn":[0.450735062],"iteration":22,"passed_time":0.07292702966,"remaining_time":3.09781339},
{"learn":[0.4503820033],"iteration":23,"passed_time":0.07604573816,"remaining_time":3.092526685},
{"learn":[0.4501382763],"iteration":24,"passed_time":0.07858103776,"remaining_time":3.064660473},
{"learn":[0.4498561385],"iteration":25,"passed_time":0.08181049479,"remaining_time":3.064746997},
{"learn":[0.4495384047],"iteration":26,"passed_time":0.08528228193,"remaining_time":3.073320753},
{"learn":[0.4492714765],"iteration":27,"passed_time":0.08805637002,"remaining_time":3.056813988},
{"learn":[0.448963725],"iteration":28,"passed_time":0.0913244932,"remaining_time":3.057795962},
{"learn":[0.4487545962],"iteration":29,"passed_time":0.09421932968,"remaining_time":3.046424993},
{"learn":[0.4486695935],"iteration":30,"passed_time":0.09639492574,"remaining_time":3.013118808},
{"learn":[0.4484751939],"iteration":31,"passed_time":0.09924767944,"remaining_time":3.002242303},
{"learn":[0.4482576986],"iteration":32,"passed_time":0.101839395,"remaining_time":2.984202877},
{"learn":[0.4481118939],"iteration":33,"passed_time":0.1043979859,"remaining_time":2.966131012},
{"learn":[0.4479604055],"iteration":34,"passed_time":0.1070929084,"remaining_time":2.952704474},
{"learn":[0.4478049644],"iteration":35,"passed_time":0.1104018644,"remaining_time":2.95631659},
{"learn":[0.4476123331],"iteration":36,"passed_time":0.1134541988,"remaining_time":2.952875497},
{"learn":[0.447513291],"iteration":37,"passed_time":0.1163424937,"remaining_time":2.945302076},
{"learn":[0.4473846678],"iteration":38,"passed_time":0.1192802046,"remaining_time":2.939186579},
{"learn":[0.4472189172],"iteration":39,"passed_time":0.1225415778,"remaining_time":2.940997868},
{"learn":[0.447070107],"iteration":40,"passed_time":0.1252082507,"remaining_time":2.928651522},
{"learn":[0.4469430954],"iteration":41,"passed_time":0.1280500462,"remaining_time":2.920760578},
{"learn":[0.4468247499],"iteration":42,"passed_time":0.1309557575,"remaining_time":2.914526976},
{"learn":[0.4467706853],"iteration":43,"passed_time":0.1334568909,"remaining_time":2.899654267},
{"learn":[0.4466763822],"iteration":44,"passed_time":0.1360366899,"remaining_time":2.887000864},
{"learn":[0.4465497976],"iteration":45,"passed_time":0.1391428569,"remaining_time":2.885701859},
{"learn":[0.4464507065],"iteration":46,"passed_time":0.1416226156,"remaining_time":2.871624525},
{"learn":[0.4463546123],"iteration":47,"passed_time":0.1445294936,"remaining_time":2.866501623},
{"learn":[0.446238562],"iteration":48,"passed_time":0.1474050387,"remaining_time":2.860861057},
{"learn":[0.446154037],"iteration":49,"passed_time":0.1500315037,"remaining_time":2.850598571},
{"learn":[0.4460368013],"iteration":50,"passed_time":0.152718968,"remaining_time":2.8417706},
{"learn":[0.4459313998],"iteration":51,"passed_time":0.1551644771,"remaining_time":2.828767775},
{"learn":[0.4458236679],"iteration":52,"passed_time":0.1580078559,"remaining_time":2.823272445},
{"learn":[0.4457724316],"iteration":53,"passed_time":0.1607164449,"remaining_time":2.815514016},
{"learn":[0.4456891033],"iteration":54,"passed_time":0.1634375754,"remaining_time":2.808154704},
{"learn":[0.4456124654],"iteration":55,"passed_time":0.1659106258,"remaining_time":2.79677912},
{"learn":[0.4455160661],"iteration":56,"passed_time":0.1682704694,"remaining_time":2.783843029},
{"learn":[0.4454530145],"iteration":57,"passed_time":0.1708626432,"remaining_time":2.775044999},
{"learn":[0.4453665909],"iteration":58,"passed_time":0.1734252341,"remaining_time":2.765985514},
{"learn":[0.4452779938],"iteration":59,"passed_time":0.176043366,"remaining_time":2.758012733},
{"learn":[0.4452153787],"iteration":60,"passed_time":0.1787295802,"remaining_time":2.751263538},
{"learn":[0.4451433149],"iteration":61,"passed_time":0.1812989627,"remaining_time":2.742877855},
{"learn":[0.4450529053],"iteration":62,"passed_time":0.1852072024,"remaining_time":2.754589661},
{"learn":[0.4449871553],"iteration":63,"passed_time":0.1882303288,"remaining_time":2.752868559},
{"learn":[0.4449197631],"iteration":64,"passed_time":0.190568006,"remaining_time":2.741247471},
{"learn":[0.4448384332],"iteration":65,"passed_time":0.1931891378,"remaining_time":2.733919011},
{"learn":[0.4447508563],"iteration":66,"passed_time":0.1958200612,"remaining_time":2.726867419},
{"learn":[0.4446479136],"iteration":67,"passed_time":0.1985829411,"remaining_time":2.721754427},
{"learn":[0.4445737329],"iteration":68,"passed_time":0.2014006536,"remaining_time":2.717449398},
{"learn":[0.4445042952],"iteration":69,"passed_time":0.203874954,"remaining_time":2.708624389},
{"learn":[0.4444307817],"iteration":70,"passed_time":0.2064702528,"remaining_time":2.701561476},
{"learn":[0.4443832128],"iteration":71,"passed_time":0.2091092593,"remaining_time":2.695186009},
{"learn":[0.4443105055],"iteration":72,"passed_time":0.2115230605,"remaining_time":2.686053111},
{"learn":[0.4442483539],"iteration":73,"passed_time":0.2140540269,"remaining_time":2.678567958},
{"learn":[0.4441772845],"iteration":74,"passed_time":0.2170301123,"remaining_time":2.676704718},
{"learn":[0.4441166254],"iteration":75,"passed_time":0.2197320347,"remaining_time":2.671478948},
{"learn":[0.4440570981],"iteration":76,"passed_time":0.222233793,"remaining_time":2.663919363},
{"learn":[0.4440138896],"iteration":77,"passed_time":0.2245948033,"remaining_time":2.654825752},
{"learn":[0.4440098753],"iteration":78,"passed_time":0.2260171594,"remaining_time":2.634959541},
{"learn":[0.4439473213],"iteration":79,"passed_time":0.2287540396,"remaining_time":2.630671456},
{"learn":[0.4438877412],"iteration":80,"passed_time":0.2313862963,"remaining_time":2.625234645},
{"learn":[0.4438569879],"iteration":81,"passed_time":0.2338157639,"remaining_time":2.617595991},
{"learn":[0.4438322514],"iteration":82,"passed_time":0.2367000589,"remaining_time":2.615107879},
{"learn":[0.4438032379],"iteration":83,"passed_time":0.239273983,"remaining_time":2.609225814},
{"learn":[0.4437331081],"iteration":84,"passed_time":0.2422341519,"remaining_time":2.6075794},
{"learn":[0.4436775584],"iteration":85,"passed_time":0.2454266928,"remaining_time":2.60837206},
{"learn":[0.4436615423],"iteration":86,"passed_time":0.2481728646,"remaining_time":2.604388797},
{"learn":[0.4435819644],"iteration":87,"passed_time":0.2509818689,"remaining_time":2.601084823},
{"learn":[0.4434975826],"iteration":88,"passed_time":0.2534955021,"remaining_time":2.594768566},
{"learn":[0.443415722],"iteration":89,"passed_time":0.2560623429,"remaining_time":2.589074801},
{"learn":[0.4433793472],"iteration":90,"passed_time":0.258915055,"remaining_time":2.586305329},
{"learn":[0.4433047193],"iteration":91,"passed_time":0.2617932667,"remaining_time":2.583785719},
{"learn":[0.4432270059],"iteration":92,"passed_time":0.2647122278,"remaining_time":2.581655813},
{"learn":[0.443222087],"iteration":93,"passed_time":0.2665222037,"remaining_time":2.568820389},
{"learn":[0.4431522913],"iteration":94,"passed_time":0.2693728325,"remaining_time":2.566130667},
{"learn":[0.4430935093],"iteration":95,"passed_time":0.2726582471,"remaining_time":2.567531827},
{"learn":[0.4430324314],"iteration":96,"passed_time":0.2754755013,"remaining_time":2.56447812},
{"learn":[0.4429654126],"iteration":97,"passed_time":0.2781222577,"remaining_time":2.559859964},
{"learn":[0.4429012089],"iteration":98,"passed_time":0.2807348896,"remaining_time":2.554971066},
{"learn":[0.4428369991],"iteration":99,"passed_time":0.2829691516,"remaining_time":2.546722364},
{"learn":[0.4427807434],"iteration":100,"passed_time":0.2857562395,"remaining_time":2.543513458},
{"learn":[0.4427278045],"iteration":101,"passed_time":0.2882487897,"remaining_time":2.537719736},
{"learn":[0.4426904538],"iteration":102,"passed_time":0.291378998,"remaining_time":2.537543313},
{"learn":[0.4426613046],"iteration":103,"passed_time":0.294559914,"remaining_time":2.537746952},
{"learn":[0.4426121709],"iteration":104,"passed_time":0.2976799558,"remaining_time":2.537367243},
{"learn":[0.4425773436],"iteration":105,"passed_time":0.3008712467,"remaining_time":2.537536741},
{"learn":[0.4425368325],"iteration":106,"passed_time":0.3039347059,"remaining_time":2.536576565},
{"learn":[0.4424929503],"iteration":107,"passed_time":0.3068320841,"remaining_time":2.534205731},
{"learn":[0.4424859056],"iteration":108,"passed_time":0.3083789801,"remaining_time":2.520785975},
{"learn":[0.442433629],"iteration":109,"passed_time":0.3110680277,"remaining_time":2.516823133},
{"learn":[0.4423635693],"iteration":110,"passed_time":0.3137626168,"remaining_time":2.512927625},
{"learn":[0.4423154996],"iteration":111,"passed_time":0.3161568767,"remaining_time":2.506672379},
{"learn":[0.4422854433],"iteration":112,"passed_time":0.3186738432,"remaining_time":2.501448663},
{"learn":[0.4422133707],"iteration":113,"passed_time":0.321019312,"remaining_time":2.494939565},
{"learn":[0.4421718989],"iteration":114,"passed_time":0.3236218607,"remaining_time":2.490481276},
{"learn":[0.4420936258],"iteration":115,"passed_time":0.3261922431,"remaining_time":2.485809853},
{"learn":[0.4420217903],"iteration":116,"passed_time":0.328909207,"remaining_time":2.482280596},
{"learn":[0.4419592139],"iteration":117,"passed_time":0.3316844201,"remaining_time":2.479200496},
{"learn":[0.4418918536],"iteration":118,"passed_time":0.3340830131,"remaining_time":2.473337265},
{"learn":[0.4418370689],"iteration":119,"passed_time":0.3366006463,"remaining_time":2.46840474},
{"learn":[0.4417546663],"iteration":120,"passed_time":0.3391452374,"remaining_time":2.463707965},
{"learn":[0.4416860094],"iteration":121,"passed_time":0.3415947049,"remaining_time":2.458361892},
{"learn":[0.4416219195],"iteration":122,"passed_time":0.3443999175,"remaining_time":2.455599412},
{"learn":[0.4415536514],"iteration":123,"passed_time":0.3469318422,"remaining_time":2.450905595},
{"learn":[0.4415266178],"iteration":124,"passed_time":0.3494411005,"remaining_time":2.446087703},
{"learn":[0.4414618547],"iteration":125,"passed_time":0.3527375149,"remaining_time":2.446766572},
{"learn":[0.4414037176],"iteration":126,"passed_time":0.3553287721,"remaining_time":2.442535575},
{"learn":[0.4413461356],"iteration":127,"passed_time":0.3579661954,"remaining_time":2.438644706},
{"learn":[0.441294668],"iteration":128,"passed_time":0.3605097865,"remaining_time":2.434139721},
{"learn":[0.4412625003],"iteration":129,"passed_time":0.363177376,"remaining_time":2.430494747},
{"learn":[0.4412332643],"iteration":130,"passed_time":0.3656304684,"remaining_time":2.425441809},
{"learn":[0.4411761072],"iteration":131,"passed_time":0.3682893497,"remaining_time":2.421781481},
{"learn":[0.4411570825],"iteration":132,"passed_time":0.3710733543,"remaining_time":2.418951866},
{"learn":[0.4411169306],"iteration":133,"passed_time":0.3735462381,"remaining_time":2.414112255},
{"learn":[0.4410590776],"iteration":134,"passed_time":0.3763085346,"remaining_time":2.411162092},
{"learn":[0.4410057126],"iteration":135,"passed_time":0.3786723365,"remaining_time":2.405683079},
{"learn":[0.4409547334],"iteration":136,"passed_time":0.3813111764,"remaining_time":2.401982082},
{"learn":[0.4408975825],"iteration":137,"passed_time":0.3836821449,"remaining_time":2.396623253},
{"learn":[0.440844034],"iteration":138,"passed_time":0.3861569453,"remaining_time":2.391950575},
{"learn":[0.4407866812],"iteration":139,"passed_time":0.3886837866,"remaining_time":2.387628975},
{"learn":[0.4407698638],"iteration":140,"passed_time":0.3914373333,"remaining_time":2.384713967},
{"learn":[0.4407303177],"iteration":141,"passed_time":0.3940474653,"remaining_time":2.380934685},
{"learn":[0.4406750624],"iteration":142,"passed_time":0.3968455947,"remaining_time":2.378298424},
{"learn":[0.4406284005],"iteration":143,"passed_time":0.3992653958,"remaining_time":2.373410964},
{"learn":[0.4405552209],"iteration":144,"passed_time":0.4020251091,"remaining_time":2.37056185},
{"learn":[0.4405125608],"iteration":145,"passed_time":0.4044053691,"remaining_time":2.365494419},
{"learn":[0.4404719602],"iteration":146,"passed_time":0.4073808295,"remaining_time":2.363917331},
{"learn":[0.4404136808],"iteration":147,"passed_time":0.4101316679,"remaining_time":2.361028251},
{"learn":[0.4403405181],"iteration":148,"passed_time":0.4127005921,"remaining_time":2.357102039},
{"learn":[0.4403036542],"iteration":149,"passed_time":0.4159820068,"remaining_time":2.357231372},
{"learn":[0.4402423355],"iteration":150,"passed_time":0.4195015849,"remaining_time":2.358654607},
{"learn":[0.4401914682],"iteration":151,"passed_time":0.4220316346,"remaining_time":2.354492277},
{"learn":[0.4401351953],"iteration":152,"passed_time":0.4245624343,"remaining_time":2.350355437},
{"learn":[0.4400911216],"iteration":153,"passed_time":0.4270791508,"remaining_time":2.346162088},
{"learn":[0.4400475794],"iteration":154,"passed_time":0.4297165323,"remaining_time":2.342648192},
{"learn":[0.4399811423],"iteration":155,"passed_time":0.4323817469,"remaining_time":2.339296118},
{"learn":[0.4399422298],"iteration":156,"passed_time":0.4357697851,"remaining_time":2.339833942},
{"learn":[0.4398807931],"iteration":157,"passed_time":0.4386685799,"remaining_time":2.337714837},
{"learn":[0.4398350952],"iteration":158,"passed_time":0.4414861674,"remaining_time":2.335156395},
{"learn":[0.4397750482],"iteration":159,"passed_time":0.4440650498,"remaining_time":2.331341511},
{"learn":[0.4396977243],"iteration":160,"passed_time":0.4463928105,"remaining_time":2.326233341},
{"learn":[0.4396639171],"iteration":161,"passed_time":0.4488897772,"remaining_time":2.322034774},
{"learn":[0.4396179498],"iteration":162,"passed_time":0.4516856984,"remaining_time":2.319392206},
{"learn":[0.4395583189],"iteration":163,"passed_time":0.4544643697,"remaining_time":2.316659836},
{"learn":[0.4394851047],"iteration":164,"passed_time":0.4574357468,"remaining_time":2.314902113},
{"learn":[0.4394411962],"iteration":165,"passed_time":0.4607580776,"remaining_time":2.314892993},
{"learn":[0.4393889439],"iteration":166,"passed_time":0.4636120397,"remaining_time":2.312507958},
{"learn":[0.4393556078],"iteration":167,"passed_time":0.4660186743,"remaining_time":2.307902006},
{"learn":[0.4392976506],"iteration":168,"passed_time":0.4685001413,"remaining_time":2.303690044},
{"learn":[0.439232303],"iteration":169,"passed_time":0.4709361922,"remaining_time":2.299276703},
{"learn":[0.4392009961],"iteration":170,"passed_time":0.4737314884,"remaining_time":2.296628093},
{"learn":[0.4391586849],"iteration":171,"passed_time":0.4762482465,"remaining_time":2.292636908},
{"learn":[0.4391146638],"iteration":172,"passed_time":0.4789940017,"remaining_time":2.289757453},
{"learn":[0.4390568876],"iteration":173,"passed_time":0.4815305096,"remaining_time":2.285886212},
{"learn":[0.4389812054],"iteration":174,"passed_time":0.4845142616,"remaining_time":2.284138662},
{"learn":[0.4389305972],"iteration":175,"passed_time":0.4876469282,"remaining_time":2.283074255},
{"learn":[0.4388708515],"iteration":176,"passed_time":0.4905118068,"remaining_time":2.280741339},
{"learn":[0.4388206874],"iteration":177,"passed_time":0.493126647,"remaining_time":2.277247774},
{"learn":[0.4387413667],"iteration":178,"passed_time":0.4952544936,"remaining_time":2.271530387},
{"learn":[0.4386987413],"iteration":179,"passed_time":0.4979527911,"remaining_time":2.268451604},
{"learn":[0.4386528115],"iteration":180,"passed_time":0.5011237489,"remaining_time":2.267515748},
{"learn":[0.4386124364],"iteration":181,"passed_time":0.5038395877,"remaining_time":2.264509795},
{"learn":[0.4385419829],"iteration":182,"passed_time":0.5066672585,"remaining_time":2.262006285},
{"learn":[0.4384826956],"iteration":183,"passed_time":0.5092835153,"remaining_time":2.258561677},
{"learn":[0.4384307647],"iteration":184,"passed_time":0.5120187706,"remaining_time":2.25565026},
{"learn":[0.4383545058],"iteration":185,"passed_time":0.5145315705,"remaining_time":2.251767196},
{"learn":[0.4382919894],"iteration":186,"passed_time":0.516896164,"remaining_time":2.247254446},
{"learn":[0.4382397733],"iteration":187,"passed_time":0.5193843392,"remaining_time":2.243298316},
{"learn":[0.4381892122],"iteration":188,"passed_time":0.5222271764,"remaining_time":2.240879577},
{"learn":[0.4381339425],"iteration":189,"passed_time":0.5247221016,"remaining_time":2.23697317},
{"learn":[0.4380570376],"iteration":190,"passed_time":0.5270844035,"remaining_time":2.232519803},
{"learn":[0.4380050398],"iteration":191,"passed_time":0.5294316222,"remaining_time":2.228024744},
{"learn":[0.4379567432],"iteration":192,"passed_time":0.5321912105,"remaining_time":2.225276201},
{"learn":[0.4379315963],"iteration":193,"passed_time":0.5349975898,"remaining_time":2.222721945},
{"learn":[0.4378715756],"iteration":194,"passed_time":0.5377567615,"remaining_time":2.21997022},
{"learn":[0.437836313],"iteration":195,"passed_time":0.5402103121,"remaining_time":2.21596475},
{"learn":[0.4377883333],"iteration":196,"passed_time":0.5428080276,"remaining_time":2.212562671},
{"learn":[0.437751944],"iteration":197,"passed_time":0.5455728241,"remaining_time":2.20984548},
{"learn":[0.4376980454],"iteration":198,"passed_time":0.5483300791,"remaining_time":2.207097454},
{"learn":[0.4376669679],"iteration":199,"passed_time":0.5511969993,"remaining_time":2.204787997},
{"learn":[0.4376115952],"iteration":200,"passed_time":0.5538440474,"remaining_time":2.201598975},
{"learn":[0.4375713725],"iteration":201,"passed_time":0.5567248424,"remaining_time":2.199338734},
{"learn":[0.4375257772],"iteration":202,"passed_time":0.5590473115,"remaining_time":2.194880331},
{"learn":[0.4374736203],"iteration":203,"passed_time":0.5617199426,"remaining_time":2.191809188},
{"learn":[0.4374335143],"iteration":204,"passed_time":0.564570238,"remaining_time":2.189430923},
{"learn":[0.4373619755],"iteration":205,"passed_time":0.566979331,"remaining_time":2.185347518},
{"learn":[0.4373037632],"iteration":206,"passed_time":0.569883084,"remaining_time":2.183175293},
{"learn":[0.4372559982],"iteration":207,"passed_time":0.572236261,"remaining_time":2.178899609},
{"learn":[0.4372082013],"iteration":208,"passed_time":0.5747693106,"remaining_time":2.175323085},
{"learn":[0.4371386909],"iteration":209,"passed_time":0.5773364432,"remaining_time":2.171884715},
{"learn":[0.4370927775],"iteration":210,"passed_time":0.5802208214,"remaining_time":2.169640892},
{"learn":[0.4370483519],"iteration":211,"passed_time":0.582757121,"remaining_time":2.166097223},
{"learn":[0.4370018719],"iteration":212,"passed_time":0.5855185843,"remaining_time":2.163394957},
{"learn":[0.4369516468],"iteration":213,"passed_time":0.5885694187,"remaining_time":2.161754968},
{"learn":[0.4369213515],"iteration":214,"passed_time":0.5920887052,"remaining_time":2.161812249},
{"learn":[0.4368799141],"iteration":215,"passed_time":0.5944227991,"remaining_time":2.157534604},
{"learn":[0.4368330529],"iteration":216,"passed_time":0.5972179703,"remaining_time":2.154938575},
{"learn":[0.4367938103],"iteration":217,"passed_time":0.5999587672,"remaining_time":2.152145669},
{"learn":[0.436726079],"iteration":218,"passed_time":0.602300236,"remaining_time":2.147929152},
{"learn":[0.436664016],"iteration":219,"passed_time":0.6051133652,"remaining_time":2.145401931},
{"learn":[0.4366247893],"iteration":220,"passed_time":0.6077406636,"remaining_time":2.14221709},
{"learn":[0.4365726093],"iteration":221,"passed_time":0.6106085005,"remaining_time":2.13988024},
{"learn":[0.4365282984],"iteration":222,"passed_time":0.6134535459,"remaining_time":2.137459216},
{"learn":[0.4364795416],"iteration":223,"passed_time":0.6163596739,"remaining_time":2.135246013},
{"learn":[0.4364321616],"iteration":224,"passed_time":0.6192655936,"remaining_time":2.133025934},
{"learn":[0.4363772051],"iteration":225,"passed_time":0.6218518092,"remaining_time":2.129704869},
{"learn":[0.4363367301],"iteration":226,"passed_time":0.6248296862,"remaining_time":2.127723998},
{"learn":[0.4362946537],"iteration":227,"passed_time":0.6277947301,"remaining_time":2.125690928},
{"learn":[0.4362321629],"iteration":228,"passed_time":0.6304086953,"remaining_time":2.122467703},
{"learn":[0.4361892664],"iteration":229,"passed_time":0.6329561198,"remaining_time":2.11902701},
{"learn":[0.4361496717],"iteration":230,"passed_time":0.6359637048,"remaining_time":2.117125926},
{"learn":[0.436084924],"iteration":231,"passed_time":0.638500671,"remaining_time":2.113657394},
{"learn":[0.4360525931],"iteration":232,"passed_time":0.6411953435,"remaining_time":2.110716002},
{"learn":[0.4359910608],"iteration":233,"passed_time":0.6443759262,"remaining_time":2.109367348},
{"learn":[0.4359478684],"iteration":234,"passed_time":0.6467707693,"remaining_time":2.10544527},
{"learn":[0.4359188515],"iteration":235,"passed_time":0.6492870691,"remaining_time":2.101929326},
{"learn":[0.435863862],"iteration":236,"passed_time":0.6520743654,"remaining_time":2.099294265},
{"learn":[0.4358171724],"iteration":237,"passed_time":0.6554929032,"remaining_time":2.098678959},
{"learn":[0.4357633126],"iteration":238,"passed_time":0.6581096184,"remaining_time":2.095487111},
{"learn":[0.435694327],"iteration":239,"passed_time":0.6608397071,"remaining_time":2.092659072},
{"learn":[0.4356625168],"iteration":240,"passed_time":0.6638190425,"remaining_time":2.090616818},
{"learn":[0.4356272768],"iteration":241,"passed_time":0.6664834237,"remaining_time":2.08758031},
{"learn":[0.4355881687],"iteration":242,"passed_time":0.6693869684,"remaining_time":2.085291914},
{"learn":[0.4355402663],"iteration":243,"passed_time":0.6727689234,"remaining_time":2.084480763},
{"learn":[0.4355071054],"iteration":244,"passed_time":0.6755838859,"remaining_time":2.081901363},
{"learn":[0.4354487082],"iteration":245,"passed_time":0.6781028524,"remaining_time":2.078412808},
{"learn":[0.4353856414],"iteration":246,"passed_time":0.6809512312,"remaining_time":2.075936344},
{"learn":[0.4353294453],"iteration":247,"passed_time":0.6833793655,"remaining_time":2.072182592},
{"learn":[0.4352696594],"iteration":248,"passed_time":0.6859194151,"remaining_time":2.068777031},
{"learn":[0.4352213535],"iteration":249,"passed_time":0.6881437605,"remaining_time":2.064431281},
{"learn":[0.4351923369],"iteration":250,"passed_time":0.6907526424,"remaining_time":2.061249917},
{"learn":[0.4351548766],"iteration":251,"passed_time":0.6933239832,"remaining_time":2.057961664},
{"learn":[0.4350996874],"iteration":252,"passed_time":0.6959962393,"remaining_time":2.054977039},
{"learn":[0.435056786],"iteration":253,"passed_time":0.6985709967,"remaining_time":2.051708518},
{"learn":[0.4350059879],"iteration":254,"passed_time":0.7008635912,"remaining_time":2.04762108},
{"learn":[0.4349643791],"iteration":255,"passed_time":0.703282559,"remaining_time":2.043914937},
{"learn":[0.4349256339],"iteration":256,"passed_time":0.7058083171,"remaining_time":2.040527547},
{"learn":[0.4348834],"iteration":257,"passed_time":0.7080559538,"remaining_time":2.036346968},
{"learn":[0.4348413324],"iteration":258,"passed_time":0.7105796703,"remaining_time":2.03297118},
{"learn":[0.4348008988],"iteration":259,"passed_time":0.7136738791,"remaining_time":2.031225656},
{"learn":[0.4347635128],"iteration":260,"passed_time":0.7173444969,"remaining_time":2.031101851},
{"learn":[0.4347010078],"iteration":261,"passed_time":0.7207227436,"remaining_time":2.030127423},
{"learn":[0.4346640198],"iteration":262,"passed_time":0.7242864879,"remaining_time":2.029654531},
{"learn":[0.434627245],"iteration":263,"passed_time":0.7268026211,"remaining_time":2.02623761},
{"learn":[0.4345866095],"iteration":264,"passed_time":0.7296888743,"remaining_time":2.023854048},
{"learn":[0.4345301556],"iteration":265,"passed_time":0.7326618765,"remaining_time":2.02170608},
{"learn":[0.4344760018],"iteration":266,"passed_time":0.7360112069,"remaining_time":2.020585074},
{"learn":[0.4344151219],"iteration":267,"passed_time":0.7385193402,"remaining_time":2.01714984},
{"learn":[0.4343876239],"iteration":268,"passed_time":0.7420759179,"remaining_time":2.016570617},
{"learn":[0.4343616953],"iteration":269,"passed_time":0.7453844155,"remaining_time":2.015298605},
{"learn":[0.4342899548],"iteration":270,"passed_time":0.7481480871,"remaining_time":2.012545961},
{"learn":[0.4342571507],"iteration":271,"passed_time":0.7507529691,"remaining_time":2.009368241},
{"learn":[0.4342235403],"iteration":272,"passed_time":0.7533408513,"remaining_time":2.006149447},
{"learn":[0.4341913757],"iteration":273,"passed_time":0.7567872221,"remaining_time":2.005209939},
{"learn":[0.4341409605],"iteration":274,"passed_time":0.7601111362,"remaining_time":2.003929359},
{"learn":[0.4341221874],"iteration":275,"passed_time":0.763185637,"remaining_time":2.001979714},
{"learn":[0.4340845005],"iteration":276,"passed_time":0.7657869774,"remaining_time":1.998786948},
{"learn":[0.4340371352],"iteration":277,"passed_time":0.7683252769,"remaining_time":1.995434712},
{"learn":[0.4339897306],"iteration":278,"passed_time":0.7715344842,"remaining_time":1.99382209},
{"learn":[0.4339516628],"iteration":279,"passed_time":0.7747761078,"remaining_time":1.99228142},
{"learn":[0.4339253001],"iteration":280,"passed_time":0.777687444,"remaining_time":1.989883531},
{"learn":[0.4338846437],"iteration":281,"passed_time":0.7806198217,"remaining_time":1.987535574},
{"learn":[0.4338579334],"iteration":282,"passed_time":0.7842938978,"remaining_time":1.987062631},
{"learn":[0.4338220575],"iteration":283,"passed_time":0.7874308977,"remaining_time":1.985213108},
{"learn":[0.4337645656],"iteration":284,"passed_time":0.7902916513,"remaining_time":1.982661511},
{"learn":[0.4337422745],"iteration":285,"passed_time":0.7933236526,"remaining_time":1.980535273},
{"learn":[0.4337177395],"iteration":286,"passed_time":0.7967442321,"remaining_time":1.979368075},
{"learn":[0.4336904765],"iteration":287,"passed_time":0.7995259868,"remaining_time":1.976605912},
{"learn":[0.4336664419],"iteration":288,"passed_time":0.8026047375,"remaining_time":1.974574285},
{"learn":[0.4336296102],"iteration":289,"passed_time":0.80592286,"remaining_time":1.973121485},
{"learn":[0.4335815979],"iteration":290,"passed_time":0.8094728544,"remaining_time":1.972220803},
{"learn":[0.4335524893],"iteration":291,"passed_time":0.8126149376,"remaining_time":1.970312931},
{"learn":[0.4334988674],"iteration":292,"passed_time":0.8152687773,"remaining_time":1.967218517},
{"learn":[0.4334600227],"iteration":293,"passed_time":0.8180668234,"remaining_time":1.964473392},
{"learn":[0.4334098002],"iteration":294,"passed_time":0.8207716624,"remaining_time":1.961505159},
{"learn":[0.4333792089],"iteration":295,"passed_time":0.823230338,"remaining_time":1.957953236},
{"learn":[0.4333510506],"iteration":296,"passed_time":0.8259736349,"remaining_time":1.955082375},
{"learn":[0.4333167492],"iteration":297,"passed_time":0.8292830075,"remaining_time":1.953545877},
{"learn":[0.4332800277],"iteration":298,"passed_time":0.8320797203,"remaining_time":1.950795598},
{"learn":[0.4332358548],"iteration":299,"passed_time":0.8348496834,"remaining_time":1.947982595},
{"learn":[0.4331950217],"iteration":300,"passed_time":0.8383621367,"remaining_time":1.946894131},
{"learn":[0.4331397599],"iteration":301,"passed_time":0.8410331845,"remaining_time":1.94384491},
{"learn":[0.4331105399],"iteration":302,"passed_time":0.8438127725,"remaining_time":1.941047863},
{"learn":[0.4330650962],"iteration":303,"passed_time":0.8471306867,"remaining_time":1.939483414},
{"learn":[0.4330181928],"iteration":304,"passed_time":0.8498272758,"remaining_time":1.936491661},
{"learn":[0.4329893146],"iteration":305,"passed_time":0.852923318,"remaining_time":1.934407786},
{"learn":[0.4329457558],"iteration":306,"passed_time":0.8557457804,"remaining_time":1.931699758},
{"learn":[0.4329100463],"iteration":307,"passed_time":0.8585874093,"remaining_time":1.929034049},
{"learn":[0.4328784344],"iteration":308,"passed_time":0.861591286,"remaining_time":1.926730028},
{"learn":[0.4328188925],"iteration":309,"passed_time":0.8644209566,"remaining_time":1.924033742},
{"learn":[0.4327621364],"iteration":310,"passed_time":0.8669382565,"remaining_time":1.920644562},
{"learn":[0.4327266874],"iteration":311,"passed_time":0.8697245944,"remaining_time":1.917854234},
{"learn":[0.4326966534],"iteration":312,"passed_time":0.8727250545,"remaining_time":1.915533906},
{"learn":[0.4326591732],"iteration":313,"passed_time":0.8753054785,"remaining_time":1.912291587},
{"learn":[0.4326116824],"iteration":314,"passed_time":0.8781628155,"remaining_time":1.909655646},
{"learn":[0.4325633134],"iteration":315,"passed_time":0.8806452824,"remaining_time":1.906206877},
{"learn":[0.4325265584],"iteration":316,"passed_time":0.8832436645,"remaining_time":1.903013952},
{"learn":[0.4324846559],"iteration":317,"passed_time":0.8861391677,"remaining_time":1.900461989},
{"learn":[0.4324539771],"iteration":318,"passed_time":0.8890383374,"remaining_time":1.897915698},
{"learn":[0.4324137999],"iteration":319,"passed_time":0.8916530526,"remaining_time":1.894762737},
{"learn":[0.4323817196],"iteration":320,"passed_time":0.8942317683,"remaining_time":1.89153698},
{"learn":[0.432346012],"iteration":321,"passed_time":0.8969814401,"remaining_time":1.888675206},
{"learn":[0.4323164681],"iteration":322,"passed_time":0.8997805695,"remaining_time":1.885917788},
{"learn":[0.4322836111],"iteration":323,"passed_time":0.9024412008,"remaining_time":1.882871147},
{"learn":[0.4322410095],"iteration":324,"passed_time":0.905378995,"remaining_time":1.880402528},
{"learn":[0.4321996156],"iteration":325,"passed_time":0.9079773771,"remaining_time":1.877229301},
{"learn":[0.4321643811],"iteration":326,"passed_time":0.9106996742,"remaining_time":1.87431462},
{"learn":[0.432122072],"iteration":327,"passed_time":0.9147555369,"remaining_time":1.874133295},
{"learn":[0.4320880181],"iteration":328,"passed_time":0.9179042867,"remaining_time":1.872078348},
{"learn":[0.4320636617],"iteration":329,"passed_time":0.920387462,"remaining_time":1.868665453},
{"learn":[0.4320095917],"iteration":330,"passed_time":0.9228721372,"remaining_time":1.865261208},
{"learn":[0.4319760965],"iteration":331,"passed_time":0.9257647238,"remaining_time":1.862683239},
{"learn":[0.4319447527],"iteration":332,"passed_time":0.9283537726,"remaining_time":1.859495394},
{"learn":[0.4319153321],"iteration":333,"passed_time":0.9308401979,"remaining_time":1.856106502},
{"learn":[0.4318853098],"iteration":334,"passed_time":0.9336241608,"remaining_time":1.853313633},
{"learn":[0.4318541943],"iteration":335,"passed_time":0.93669487,"remaining_time":1.851087481},
{"learn":[0.4318185711],"iteration":336,"passed_time":0.9394730414,"remaining_time":1.848280791},
{"learn":[0.4317903715],"iteration":337,"passed_time":0.9418261767,"remaining_time":1.844641802},
{"learn":[0.4317465164],"iteration":338,"passed_time":0.9443720178,"remaining_time":1.841386147},
{"learn":[0.4317090469],"iteration":339,"passed_time":0.947017691,"remaining_time":1.838328459},
{"learn":[0.4316648365],"iteration":340,"passed_time":0.9497249466,"remaining_time":1.835392199},
{"learn":[0.4316371082],"iteration":341,"passed_time":0.952304579,"remaining_time":1.832211734},
{"learn":[0.4316038715],"iteration":342,"passed_time":0.9552292067,"remaining_time":1.829695594},
{"learn":[0.4315779493],"iteration":343,"passed_time":0.9578925046,"remaining_time":1.82667873},
{"learn":[0.4315320559],"iteration":344,"passed_time":0.9604205543,"remaining_time":1.823407139},
{"learn":[0.4314764365],"iteration":345,"passed_time":0.9628797716,"remaining_time":1.820009742},
{"learn":[0.4314335014],"iteration":346,"passed_time":0.9658945231,"remaining_time":1.81766318},
{"learn":[0.4314124759],"iteration":347,"passed_time":0.9686720278,"remaining_time":1.814868282},
{"learn":[0.4313798271],"iteration":348,"passed_time":0.9714174497,"remaining_time":1.812013638},
{"learn":[0.4313576332],"iteration":349,"passed_time":0.9737112108,"remaining_time":1.80832082},
{"learn":[0.4313175414],"iteration":350,"passed_time":0.9762924681,"remaining_time":1.805167555},
{"learn":[0.4312849964],"iteration":351,"passed_time":0.9786266871,"remaining_time":1.801562765},
{"learn":[0.4312496135],"iteration":352,"passed_time":0.9814040251,"remaining_time":1.798777349},
{"learn":[0.4312238135],"iteration":353,"passed_time":0.984190738,"remaining_time":1.796009087},
{"learn":[0.4311805193],"iteration":354,"passed_time":0.9867382041,"remaining_time":1.792806033},
{"learn":[0.4311388941],"iteration":355,"passed_time":0.9897184145,"remaining_time":1.790389491},
{"learn":[0.4311061854],"iteration":356,"passed_time":0.9921992981,"remaining_time":1.787070445},
{"learn":[0.4310514727],"iteration":357,"passed_time":0.994660932,"remaining_time":1.78372156},
{"learn":[0.4310183332],"iteration":358,"passed_time":0.9978628061,"remaining_time":1.781699328},
{"learn":[0.4309822806],"iteration":359,"passed_time":1.000509771,"remaining_time":1.778684037},
{"learn":[0.4309469616],"iteration":360,"passed_time":1.003116153,"remaining_time":1.775598952},
{"learn":[0.4309182318],"iteration":361,"passed_time":1.005657577,"remaining_time":1.772402029},
{"learn":[0.4308909084],"iteration":362,"passed_time":1.00812017,"remaining_time":1.76907038},
{"learn":[0.4308666138],"iteration":363,"passed_time":1.010735468,"remaining_time":1.766010323},
{"learn":[0.4308358423],"iteration":364,"passed_time":1.013644138,"remaining_time":1.763463089},
{"learn":[0.430807017],"iteration":365,"passed_time":1.015800109,"remaining_time":1.759610025},
{"learn":[0.4307810831],"iteration":366,"passed_time":1.018389533,"remaining_time":1.756513827},
{"learn":[0.4307426143],"iteration":367,"passed_time":1.021341619,"remaining_time":1.754043215},
{"learn":[0.4307173367],"iteration":368,"passed_time":1.0259041,"remaining_time":1.754323813},
{"learn":[0.4306923614],"iteration":369,"passed_time":1.029049558,"remaining_time":1.752165463},
{"learn":[0.4306628387],"iteration":370,"passed_time":1.03227964,"remaining_time":1.750145265},
{"learn":[0.4306327732],"iteration":371,"passed_time":1.035075728,"remaining_time":1.747385906},
{"learn":[0.430617243],"iteration":372,"passed_time":1.038081063,"remaining_time":1.744978087},
{"learn":[0.4305894106],"iteration":373,"passed_time":1.04064882,"remaining_time":1.741834656},
{"learn":[0.4305578544],"iteration":374,"passed_time":1.042935665,"remaining_time":1.738226108},
{"learn":[0.4305219567],"iteration":375,"passed_time":1.045907375,"remaining_time":1.735761176},
{"learn":[0.4304862111],"iteration":376,"passed_time":1.048028514,"remaining_time":1.731887968},
{"learn":[0.4304466664],"iteration":377,"passed_time":1.05066827,"remaining_time":1.728877418},
{"learn":[0.43040169],"iteration":378,"passed_time":1.053157237,"remaining_time":1.725621753},
{"learn":[0.4303457617],"iteration":379,"passed_time":1.056026116,"remaining_time":1.722989978},
{"learn":[0.4303158893],"iteration":380,"passed_time":1.058606373,"remaining_time":1.719888044},
{"learn":[0.4302805563],"iteration":381,"passed_time":1.061182005,"remaining_time":1.716781359},
{"learn":[0.4302377937],"iteration":382,"passed_time":1.063583973,"remaining_time":1.71339768},
{"learn":[0.4302021715],"iteration":383,"passed_time":1.066135689,"remaining_time":1.710259335},
{"learn":[0.430165099],"iteration":384,"passed_time":1.068452159,"remaining_time":1.706748253},
{"learn":[0.430119259],"iteration":385,"passed_time":1.071079582,"remaining_time":1.703737988},
{"learn":[0.4300770402],"iteration":386,"passed_time":1.073676506,"remaining_time":1.70068139},
{"learn":[0.4300560979],"iteration":387,"passed_time":1.076314512,"remaining_time":1.697691963},
{"learn":[0.4300194393],"iteration":388,"passed_time":1.0791431,"remaining_time":1.695003686},
{"learn":[0.4299922584],"iteration":389,"passed_time":1.081143656,"remaining_time":1.691019565},
{"learn":[0.4299693008],"iteration":390,"passed_time":1.083893245,"remaining_time":1.688212241},
{"learn":[0.4299247392],"iteration":391,"passed_time":1.086509085,"remaining_time":1.685197764},
{"learn":[0.4298864434],"iteration":392,"passed_time":1.088966886,"remaining_time":1.68194122},
{"learn":[0.4298539347],"iteration":393,"passed_time":1.091571518,"remaining_time":1.678914568},
{"learn":[0.4297961325],"iteration":394,"passed_time":1.094133067,"remaining_time":1.675824064},
{"learn":[0.4297780589],"iteration":395,"passed_time":1.096984154,"remaining_time":1.673177851},
{"learn":[0.4297314765],"iteration":396,"passed_time":1.099480954,"remaining_time":1.669992482},
{"learn":[0.4297037282],"iteration":397,"passed_time":1.101802965,"remaining_time":1.666546193},
{"learn":[0.4296673558],"iteration":398,"passed_time":1.104094434,"remaining_time":1.663059536},
{"learn":[0.4296369075],"iteration":399,"passed_time":1.106686025,"remaining_time":1.660029037},
{"learn":[0.4295999935],"iteration":400,"passed_time":1.109582528,"remaining_time":1.657456195},
{"learn":[0.4295744302],"iteration":401,"passed_time":1.112521739,"remaining_time":1.654945273},
{"learn":[0.4295546411],"iteration":402,"passed_time":1.115289619,"remaining_time":1.652178418},
{"learn":[0.4295272427],"iteration":403,"passed_time":1.119064902,"remaining_time":1.650897726},
{"learn":[0.4294870715],"iteration":404,"passed_time":1.121778532,"remaining_time":1.648045004},
{"learn":[0.4294561492],"iteration":405,"passed_time":1.125488483,"remaining_time":1.646650638},
{"learn":[0.4294202577],"iteration":406,"passed_time":1.128082615,"remaining_time":1.643619142},
{"learn":[0.4293842099],"iteration":407,"passed_time":1.130919952,"remaining_time":1.640942676},
{"learn":[0.4293444649],"iteration":408,"passed_time":1.133932204,"remaining_time":1.638518172},
{"learn":[0.4293139197],"iteration":409,"passed_time":1.136649709,"remaining_time":1.635666655},
{"learn":[0.4292780639],"iteration":410,"passed_time":1.139396215,"remaining_time":1.632857349},
{"learn":[0.4292489779],"iteration":411,"passed_time":1.14224826,"remaining_time":1.630198973},
{"learn":[0.4292217788],"iteration":412,"passed_time":1.144957307,"remaining_time":1.627336415},
{"learn":[0.4291736295],"iteration":413,"passed_time":1.14786956,"remaining_time":1.624762228},
{"learn":[0.4291524492],"iteration":414,"passed_time":1.150974852,"remaining_time":1.622458527},
{"learn":[0.4291371885],"iteration":415,"passed_time":1.153717399,"remaining_time":1.619641733},
{"learn":[0.4291177958],"iteration":416,"passed_time":1.156429738,"remaining_time":1.616783063},
{"learn":[0.4290677142],"iteration":417,"passed_time":1.159368199,"remaining_time":1.614239932},
{"learn":[0.4290253833],"iteration":418,"passed_time":1.162473991,"remaining_time":1.611926942},
{"learn":[0.42900428],"iteration":419,"passed_time":1.165254412,"remaining_time":1.609160855},
{"learn":[0.4289784869],"iteration":420,"passed_time":1.168170873,"remaining_time":1.606581795},
{"learn":[0.4289517774],"iteration":421,"passed_time":1.170747672,"remaining_time":1.603535912},
{"learn":[0.4289239844],"iteration":422,"passed_time":1.173693133,"remaining_time":1.600995125},
{"learn":[0.4288979242],"iteration":423,"passed_time":1.176775509,"remaining_time":1.598638427},
{"learn":[0.4288798612],"iteration":424,"passed_time":1.179741386,"remaining_time":1.596120699},
{"learn":[0.4288457856],"iteration":425,"passed_time":1.182676889,"remaining_time":1.593559939},
{"learn":[0.4288146607],"iteration":426,"passed_time":1.185451893,"remaining_time":1.590782049},
{"learn":[0.4287902758],"iteration":427,"passed_time":1.188862681,"remaining_time":1.588853864},
{"learn":[0.4287657438],"iteration":428,"passed_time":1.191913266,"remaining_time":1.586439335},
{"learn":[0.4287196197],"iteration":429,"passed_time":1.19572284,"remaining_time":1.585027951},
{"learn":[0.4287001374],"iteration":430,"passed_time":1.198325222,"remaining_time":1.58201172},
{"learn":[0.428674437],"iteration":431,"passed_time":1.201246642,"remaining_time":1.579416881},
{"learn":[0.4286618571],"iteration":432,"passed_time":1.204211186,"remaining_time":1.576877003},
{"learn":[0.4286430206],"iteration":433,"passed_time":1.207254395,"remaining_time":1.574437759},
{"learn":[0.4285912104],"iteration":434,"passed_time":1.210123565,"remaining_time":1.571769688},
{"learn":[0.4285763227],"iteration":435,"passed_time":1.213011777,"remaining_time":1.569125326},
{"learn":[0.428554674],"iteration":436,"passed_time":1.215562326,"remaining_time":1.566044828},
{"learn":[0.428541781],"iteration":437,"passed_time":1.217770797,"remaining_time":1.562527826},
{"learn":[0.4284876832],"iteration":438,"passed_time":1.220328888,"remaining_time":1.559463567},
{"learn":[0.4284726168],"iteration":439,"passed_time":1.223908132,"remaining_time":1.557701259},
{"learn":[0.4284270806],"iteration":440,"passed_time":1.226372391,"remaining_time":1.554517384},
{"learn":[0.4283940086],"iteration":441,"passed_time":1.229439641,"remaining_time":1.552098009},
{"learn":[0.4283672862],"iteration":442,"passed_time":1.232551933,"remaining_time":1.549732341},
{"learn":[0.4283464043],"iteration":443,"passed_time":1.235258689,"remaining_time":1.546855476},
{"learn":[0.4283130697],"iteration":444,"passed_time":1.238289357,"remaining_time":1.544383355},
{"learn":[0.4282717156],"iteration":445,"passed_time":1.240812032,"remaining_time":1.541277726},
{"learn":[0.4282305201],"iteration":446,"passed_time":1.243789117,"remaining_time":1.538736872},
{"learn":[0.4281947855],"iteration":447,"passed_time":1.246637329,"remaining_time":1.536035281},
{"learn":[0.4281791557],"iteration":448,"passed_time":1.249688789,"remaining_time":1.533582456},
{"learn":[0.4281642767],"iteration":449,"passed_time":1.252389044,"remaining_time":1.530697721},
{"learn":[0.4281418657],"iteration":450,"passed_time":1.255291131,"remaining_time":1.528059492},
{"learn":[0.4281073807],"iteration":451,"passed_time":1.258097135,"remaining_time":1.525303606},
{"learn":[0.4280749233],"iteration":452,"passed_time":1.26146109,"remaining_time":1.523221228},
{"learn":[0.4280467069],"iteration":453,"passed_time":1.264774421,"remaining_time":1.521072322},
{"learn":[0.4280247064],"iteration":454,"passed_time":1.267553509,"remaining_time":1.518278379},
{"learn":[0.4279835708],"iteration":455,"passed_time":1.270629927,"remaining_time":1.515839211},
{"learn":[0.4279496372],"iteration":456,"passed_time":1.273457056,"remaining_time":1.513101053},
{"learn":[0.4279297447],"iteration":457,"passed_time":1.276523432,"remaining_time":1.510645633},
{"learn":[0.4279031506],"iteration":458,"passed_time":1.278950108,"remaining_time":1.507433569},
{"learn":[0.4278543787],"iteration":459,"passed_time":1.281678071,"remaining_time":1.504578606},
{"learn":[0.4278121884],"iteration":460,"passed_time":1.284129039,"remaining_time":1.50140033},
{"learn":[0.4277948337],"iteration":461,"passed_time":1.286573506,"remaining_time":1.498217633},
{"learn":[0.4277752613],"iteration":462,"passed_time":1.289207263,"remaining_time":1.495257668},
{"learn":[0.4277247131],"iteration":463,"passed_time":1.291960476,"remaining_time":1.492437102},
{"learn":[0.4276864693],"iteration":464,"passed_time":1.294775397,"remaining_time":1.489687823},
{"learn":[0.4276580389],"iteration":465,"passed_time":1.297845148,"remaining_time":1.487230277},
{"learn":[0.4276342779],"iteration":466,"passed_time":1.300734985,"remaining_time":1.484564768},
{"learn":[0.4276043065],"iteration":467,"passed_time":1.30395865,"remaining_time":1.482277782},
{"learn":[0.4275854549],"iteration":468,"passed_time":1.306870528,"remaining_time":1.479633796},
{"learn":[0.4275585565],"iteration":469,"passed_time":1.30943741,"remaining_time":1.476599633},
{"learn":[0.4275327946],"iteration":470,"passed_time":1.312291497,"remaining_time":1.473890026},
{"learn":[0.4274931309],"iteration":471,"passed_time":1.314978795,"remaining_time":1.470993228},
{"learn":[0.4274394066],"iteration":472,"passed_time":1.317268431,"remaining_time":1.467654256},
{"learn":[0.4274093157],"iteration":473,"passed_time":1.319766815,"remaining_time":1.46455136},
{"learn":[0.4273681343],"iteration":474,"passed_time":1.322572819,"remaining_time":1.46179101},
{"learn":[0.4273322591],"iteration":475,"passed_time":1.325016578,"remaining_time":1.458631695},
{"learn":[0.427307293],"iteration":476,"passed_time":1.327523545,"remaining_time":1.455544683},
{"learn":[0.4272822707],"iteration":477,"passed_time":1.329998054,"remaining_time":1.452424653},
{"learn":[0.4272591103],"iteration":478,"passed_time":1.332501729,"remaining_time":1.449339041},
{"learn":[0.4272236206],"iteration":479,"passed_time":1.335143777,"remaining_time":1.446405758},
{"learn":[0.4271838936],"iteration":480,"passed_time":1.337778492,"remaining_time":1.443465774},
{"learn":[0.4271676838],"iteration":481,"passed_time":1.340278958,"remaining_time":1.440382781},
{"learn":[0.4271399431],"iteration":482,"passed_time":1.342859216,"remaining_time":1.437387608},
{"learn":[0.4270991356],"iteration":483,"passed_time":1.346239671,"remaining_time":1.435247252},
{"learn":[0.4270713002],"iteration":484,"passed_time":1.348873802,"remaining_time":1.432309295},
{"learn":[0.427040568],"iteration":485,"passed_time":1.354217481,"remaining_time":1.432238241},
{"learn":[0.4269970054],"iteration":486,"passed_time":1.35734869,"remaining_time":1.429814944},
{"learn":[0.4269740057],"iteration":487,"passed_time":1.360508398,"remaining_time":1.427418647},
{"learn":[0.4269538803],"iteration":488,"passed_time":1.362842658,"remaining_time":1.424156643},
{"learn":[0.4269242455],"iteration":489,"passed_time":1.368868703,"remaining_time":1.424740895},
{"learn":[0.426904004],"iteration":490,"passed_time":1.372259116,"remaining_time":1.422565968},
{"learn":[0.4268681046],"iteration":491,"passed_time":1.374969997,"remaining_time":1.419684468},
{"learn":[0.4268452032],"iteration":492,"passed_time":1.377583337,"remaining_time":1.416703351},
{"learn":[0.4268200925],"iteration":493,"passed_time":1.380528964,"remaining_time":1.414064081},
{"learn":[0.4267818148],"iteration":494,"passed_time":1.383318927,"remaining_time":1.411264764},
{"learn":[0.4267468855],"iteration":495,"passed_time":1.386116973,"remaining_time":1.408473699},
{"learn":[0.4267144718],"iteration":496,"passed_time":1.389447554,"remaining_time":1.406221569},
{"learn":[0.4267045522],"iteration":497,"passed_time":1.392295225,"remaining_time":1.403478319},
{"learn":[0.4266529635],"iteration":498,"passed_time":1.394955439,"remaining_time":1.400546443},
{"learn":[0.426609631],"iteration":499,"passed_time":1.397949941,"remaining_time":1.397949941},
{"learn":[0.4265877463],"iteration":500,"passed_time":1.400622739,"remaining_time":1.39503143},
{"learn":[0.4265646437],"iteration":501,"passed_time":1.403763405,"remaining_time":1.39257804},
{"learn":[0.4265410652],"iteration":502,"passed_time":1.406307121,"remaining_time":1.389532086},
{"learn":[0.426507567],"iteration":503,"passed_time":1.40915625,"remaining_time":1.386788691},
{"learn":[0.4264920555],"iteration":504,"passed_time":1.412066878,"remaining_time":1.384105158},
{"learn":[0.4264424807],"iteration":505,"passed_time":1.414858508,"remaining_time":1.381304551},
{"learn":[0.4264053964],"iteration":506,"passed_time":1.417400682,"remaining_time":1.378261413},
{"learn":[0.426386771],"iteration":507,"passed_time":1.419612444,"remaining_time":1.374900241},
{"learn":[0.4263599612],"iteration":508,"passed_time":1.421990579,"remaining_time":1.371704076},
{"learn":[0.4263461616],"iteration":509,"passed_time":1.424650586,"remaining_time":1.368781935},
{"learn":[0.4263278097],"iteration":510,"passed_time":1.427120303,"remaining_time":1.365678724},
{"learn":[0.4263041603],"iteration":511,"passed_time":1.42985585,"remaining_time":1.362831357},
{"learn":[0.4262759818],"iteration":512,"passed_time":1.432405399,"remaining_time":1.359807855},
{"learn":[0.4262451979],"iteration":513,"passed_time":1.434803076,"remaining_time":1.356642597},
{"learn":[0.4262027924],"iteration":514,"passed_time":1.437550456,"remaining_time":1.353809653},
{"learn":[0.4261628384],"iteration":515,"passed_time":1.439966799,"remaining_time":1.350666532},
{"learn":[0.4261405887],"iteration":516,"passed_time":1.443001175,"remaining_time":1.348103612},
{"learn":[0.4261203296],"iteration":517,"passed_time":1.445552766,"remaining_time":1.345089639},
{"learn":[0.4260944428],"iteration":518,"passed_time":1.44847156,"remaining_time":1.342417766},
{"learn":[0.4260751351],"iteration":519,"passed_time":1.451173108,"remaining_time":1.339544407},
{"learn":[0.4260551258],"iteration":520,"passed_time":1.453862697,"remaining_time":1.336660714},
{"learn":[0.4260061966],"iteration":521,"passed_time":1.456618785,"remaining_time":1.333838658},
{"learn":[0.4259643416],"iteration":522,"passed_time":1.459241709,"remaining_time":1.330895402},
{"learn":[0.4259139545],"iteration":523,"passed_time":1.461514845,"remaining_time":1.327635623},
{"learn":[0.4258923073],"iteration":524,"passed_time":1.463947688,"remaining_time":1.324524099},
{"learn":[0.4258550436],"iteration":525,"passed_time":1.466397864,"remaining_time":1.321430774},
{"learn":[0.4258282246],"iteration":526,"passed_time":1.469323866,"remaining_time":1.318766962},
{"learn":[0.4258035881],"iteration":527,"passed_time":1.471723918,"remaining_time":1.315631987},
{"learn":[0.4257662248],"iteration":528,"passed_time":1.474495923,"remaining_time":1.312830963},
{"learn":[0.4257333972],"iteration":529,"passed_time":1.477278136,"remaining_time":1.310039101},
{"learn":[0.425710907],"iteration":530,"passed_time":1.480115889,"remaining_time":1.307296332},
{"learn":[0.4256912017],"iteration":531,"passed_time":1.48329568,"remaining_time":1.304854095},
{"learn":[0.4256568519],"iteration":532,"passed_time":1.486220767,"remaining_time":1.302185925},
{"learn":[0.4256288898],"iteration":533,"passed_time":1.489350225,"remaining_time":1.29969514},
{"learn":[0.4256011241],"iteration":534,"passed_time":1.492325519,"remaining_time":1.297067974},
{"learn":[0.4255664226],"iteration":535,"passed_time":1.49519848,"remaining_time":1.294350923},
{"learn":[0.4255239328],"iteration":536,"passed_time":1.498425979,"remaining_time":1.291938973},
{"learn":[0.4255068935],"iteration":537,"passed_time":1.501451981,"remaining_time":1.289350957},
{"learn":[0.4254840184],"iteration":538,"passed_time":1.504199486,"remaining_time":1.286523122},
{"learn":[0.4254605915],"iteration":539,"passed_time":1.507993352,"remaining_time":1.284586929},
{"learn":[0.4254275988],"iteration":540,"passed_time":1.51102827,"remaining_time":1.281999955},
{"learn":[0.4254108452],"iteration":541,"passed_time":1.514116312,"remaining_time":1.279456219},
{"learn":[0.4253641003],"iteration":542,"passed_time":1.516814693,"remaining_time":1.276582531},
{"learn":[0.4253491903],"iteration":543,"passed_time":1.52025498,"remaining_time":1.274331381},
{"learn":[0.4253265575],"iteration":544,"passed_time":1.522954236,"remaining_time":1.271457206},
{"learn":[0.4252794733],"iteration":545,"passed_time":1.525678075,"remaining_time":1.268604114},
{"learn":[0.4252400599],"iteration":546,"passed_time":1.528359831,"remaining_time":1.265716642},
{"learn":[0.4252147604],"iteration":547,"passed_time":1.530964588,"remaining_time":1.262766412},
{"learn":[0.4251949375],"iteration":548,"passed_time":1.533666802,"remaining_time":1.2598975},
{"learn":[0.4251704546],"iteration":549,"passed_time":1.536228684,"remaining_time":1.256914378},
{"learn":[0.4251398229],"iteration":550,"passed_time":1.53935281,"remaining_time":1.254390946},
{"learn":[0.4251159607],"iteration":551,"passed_time":1.542097398,"remaining_time":1.251557309},
{"learn":[0.4250839259],"iteration":552,"passed_time":1.544836237,"remaining_time":1.248719345},
{"learn":[0.4250489045],"iteration":553,"passed_time":1.547793072,"remaining_time":1.246057239},
{"learn":[0.4250230963],"iteration":554,"passed_time":1.550492661,"remaining_time":1.24318781},
{"learn":[0.424994354],"iteration":555,"passed_time":1.553238958,"remaining_time":1.24035629},
{"learn":[0.424978141],"iteration":556,"passed_time":1.556057046,"remaining_time":1.237582175},
{"learn":[0.4249600972],"iteration":557,"passed_time":1.558857883,"remaining_time":1.234794237},
{"learn":[0.4249161999],"iteration":558,"passed_time":1.561394475,"remaining_time":1.231797788},
{"learn":[0.4248848519],"iteration":559,"passed_time":1.564185812,"remaining_time":1.229003138},
{"learn":[0.4248545241],"iteration":560,"passed_time":1.566860985,"remaining_time":1.226117598},
{"learn":[0.4248285079],"iteration":561,"passed_time":1.569590866,"remaining_time":1.223275443},
{"learn":[0.4247998516],"iteration":562,"passed_time":1.57199875,"remaining_time":1.220183755},
{"learn":[0.4247810008],"iteration":563,"passed_time":1.574639632,"remaining_time":1.217274609},
{"learn":[0.4247442646],"iteration":564,"passed_time":1.577324596,"remaining_time":1.214400353},
{"learn":[0.4247308061],"iteration":565,"passed_time":1.580039352,"remaining_time":1.211549609},
{"learn":[0.4247104957],"iteration":566,"passed_time":1.582788273,"remaining_time":1.208725436},
{"learn":[0.4246822227],"iteration":567,"passed_time":1.585597986,"remaining_time":1.205947764},
{"learn":[0.424662057],"iteration":568,"passed_time":1.587781082,"remaining_time":1.202695336},
{"learn":[0.4246286501],"iteration":569,"passed_time":1.590473879,"remaining_time":1.199831172},
{"learn":[0.4245952783],"iteration":570,"passed_time":1.593169468,"remaining_time":1.196969706},
{"learn":[0.4245665818],"iteration":571,"passed_time":1.595695935,"remaining_time":1.193982273},
{"learn":[0.4245442375],"iteration":572,"passed_time":1.598377066,"remaining_time":1.191111705},
{"learn":[0.4245146545],"iteration":573,"passed_time":1.601078363,"remaining_time":1.188256764},
{"learn":[0.4244923384],"iteration":574,"passed_time":1.603517372,"remaining_time":1.185208493},
{"learn":[0.4244512388],"iteration":575,"passed_time":1.606254003,"remaining_time":1.182381419},
{"learn":[0.4244207896],"iteration":576,"passed_time":1.609479626,"remaining_time":1.17991314},
{"learn":[0.4243926467],"iteration":577,"passed_time":1.612204674,"remaining_time":1.177076769},
{"learn":[0.4243559912],"iteration":578,"passed_time":1.614939679,"remaining_time":1.174248022},
{"learn":[0.4243328226],"iteration":579,"passed_time":1.6177261,"remaining_time":1.171456831},
{"learn":[0.4243119085],"iteration":580,"passed_time":1.62013661,"remaining_time":1.16839456},
{"learn":[0.4242654243],"iteration":581,"passed_time":1.622950656,"remaining_time":1.165624354},
{"learn":[0.4242479602],"iteration":582,"passed_time":1.625905366,"remaining_time":1.16295461},
{"learn":[0.42420595],"iteration":583,"passed_time":1.629603442,"remaining_time":1.160813411},
{"learn":[0.4241753877],"iteration":584,"passed_time":1.63240828,"remaining_time":1.158033224},
{"learn":[0.4241567527],"iteration":585,"passed_time":1.635251367,"remaining_time":1.155279976},
{"learn":[0.4241346071],"iteration":586,"passed_time":1.637802666,"remaining_time":1.152321126},
{"learn":[0.4240915955],"iteration":587,"passed_time":1.640111761,"remaining_time":1.149193955},
{"learn":[0.42406956],"iteration":588,"passed_time":1.643117137,"remaining_time":1.146555422},
{"learn":[0.4240431715],"iteration":589,"passed_time":1.645926517,"remaining_time":1.143779444},
{"learn":[0.4240173813],"iteration":590,"passed_time":1.648987559,"remaining_time":1.141177516},
{"learn":[0.4239731076],"iteration":591,"passed_time":1.651968103,"remaining_time":1.138518557},
{"learn":[0.423955812],"iteration":592,"passed_time":1.654653025,"remaining_time":1.135655618},
{"learn":[0.4239235149],"iteration":593,"passed_time":1.657407072,"remaining_time":1.132840524},
{"learn":[0.4238841924],"iteration":594,"passed_time":1.659979871,"remaining_time":1.129902265},
{"learn":[0.4238406745],"iteration":595,"passed_time":1.662408131,"remaining_time":1.126867256},
{"learn":[0.4237988952],"iteration":596,"passed_time":1.664922014,"remaining_time":1.12389208},
{"learn":[0.4237809386],"iteration":597,"passed_time":1.668296427,"remaining_time":1.121496929},
{"learn":[0.4237700491],"iteration":598,"passed_time":1.671512884,"remaining_time":1.118992766},
{"learn":[0.4237466487],"iteration":599,"passed_time":1.674143349,"remaining_time":1.116095566},
{"learn":[0.4237240493],"iteration":600,"passed_time":1.676785814,"remaining_time":1.113207221},
{"learn":[0.4236935871],"iteration":601,"passed_time":1.679525528,"remaining_time":1.110383987},
{"learn":[0.4236649075],"iteration":602,"passed_time":1.682284199,"remaining_time":1.107573511},
{"learn":[0.4236363817],"iteration":603,"passed_time":1.685188327,"remaining_time":1.104858572},
{"learn":[0.4236247498],"iteration":604,"passed_time":1.688015957,"remaining_time":1.102093063},
{"learn":[0.4235832307],"iteration":605,"passed_time":1.690969001,"remaining_time":1.099408888},
{"learn":[0.4235466432],"iteration":606,"passed_time":1.693922045,"remaining_time":1.096723828},
{"learn":[0.4235251238],"iteration":607,"passed_time":1.69650976,"remaining_time":1.093802345},
{"learn":[0.4235029265],"iteration":608,"passed_time":1.699681885,"remaining_time":1.091257171},
{"learn":[0.423484273],"iteration":609,"passed_time":1.702354766,"remaining_time":1.088390752},
{"learn":[0.4234495258],"iteration":610,"passed_time":1.704983272,"remaining_time":1.085496715},
{"learn":[0.4234252109],"iteration":611,"passed_time":1.708490017,"remaining_time":1.083160338},
{"learn":[0.4234073979],"iteration":612,"passed_time":1.710897277,"remaining_time":1.080126013},
{"learn":[0.4233900035],"iteration":613,"passed_time":1.713455035,"remaining_time":1.077188344},
{"learn":[0.4233574424],"iteration":614,"passed_time":1.716130374,"remaining_time":1.074325519},
{"learn":[0.4233226367],"iteration":615,"passed_time":1.718881504,"remaining_time":1.071510548},
{"learn":[0.4232870193],"iteration":616,"passed_time":1.7217108,"remaining_time":1.068744305},
{"learn":[0.4232631447],"iteration":617,"passed_time":1.724390598,"remaining_time":1.06588545},
{"learn":[0.4232363834],"iteration":618,"passed_time":1.726989521,"remaining_time":1.062977395},
{"learn":[0.4232143263],"iteration":619,"passed_time":1.729988106,"remaining_time":1.060315291},
{"learn":[0.423185951],"iteration":620,"passed_time":1.732484906,"remaining_time":1.057345861},
{"learn":[0.4231535027],"iteration":621,"passed_time":1.735081039,"remaining_time":1.054438316},
{"learn":[0.4231205889],"iteration":622,"passed_time":1.737670504,"remaining_time":1.051527737},
{"learn":[0.4230883129],"iteration":623,"passed_time":1.740139888,"remaining_time":1.04854583},
{"learn":[0.4230690723],"iteration":624,"passed_time":1.743083682,"remaining_time":1.045850209},
{"learn":[0.4230441988],"iteration":625,"passed_time":1.745568732,"remaining_time":1.042879722},
{"learn":[0.4230065807],"iteration":626,"passed_time":1.748169198,"remaining_time":1.039979443},
{"learn":[0.4229720831],"iteration":627,"passed_time":1.751151533,"remaining_time":1.037306322},
{"learn":[0.4229520423],"iteration":628,"passed_time":1.753731749,"remaining_time":1.034395038},
{"learn":[0.4229163164],"iteration":629,"passed_time":1.756246174,"remaining_time":1.031446165},
{"learn":[0.4228779663],"iteration":630,"passed_time":1.759237634,"remaining_time":1.028777634},
{"learn":[0.4228489714],"iteration":631,"passed_time":1.761982056,"remaining_time":1.025964235},
{"learn":[0.4228239561],"iteration":632,"passed_time":1.764410023,"remaining_time":1.022967581},
{"learn":[0.4227911117],"iteration":633,"passed_time":1.767593439,"remaining_time":1.020408831},
{"learn":[0.4227750513],"iteration":634,"passed_time":1.770260946,"remaining_time":1.017551567},
{"learn":[0.4227523006],"iteration":635,"passed_time":1.77328553,"remaining_time":1.014899266},
{"learn":[0.4227198868],"iteration":636,"passed_time":1.775840121,"remaining_time":1.011977966},
{"learn":[0.422681752],"iteration":637,"passed_time":1.778881122,"remaining_time":1.009333803},
{"learn":[0.4226707626],"iteration":638,"passed_time":1.781710918,"remaining_time":1.006569079},
{"learn":[0.4226493027],"iteration":639,"passed_time":1.784457548,"remaining_time":1.003757371},
{"learn":[0.4226127709],"iteration":640,"passed_time":1.78685385,"remaining_time":1.00074966},
{"learn":[0.4225884814],"iteration":641,"passed_time":1.789528022,"remaining_time":0.9978988038},
{"learn":[0.4225523443],"iteration":642,"passed_time":1.79221057,"remaining_time":0.995053147},
{"learn":[0.4225415787],"iteration":643,"passed_time":1.794949242,"remaining_time":0.992239022},
{"learn":[0.422494279],"iteration":644,"passed_time":1.797523499,"remaining_time":0.9893346392},
{"learn":[0.4224721556],"iteration":645,"passed_time":1.800369212,"remaining_time":0.9865800323},
{"learn":[0.422456495],"iteration":646,"passed_time":1.803073092,"remaining_time":0.9837477613},
{"learn":[0.4224080575],"iteration":647,"passed_time":1.805469144,"remaining_time":0.9807486707},
{"learn":[0.4223874641],"iteration":648,"passed_time":1.807965985,"remaining_time":0.977805949},
{"learn":[0.4223645315],"iteration":649,"passed_time":1.810870739,"remaining_time":0.9750842438},
{"learn":[0.422335893],"iteration":650,"passed_time":1.813771617,"remaining_time":0.9723598989},
{"learn":[0.4223204651],"iteration":651,"passed_time":1.816333499,"remaining_time":0.9694540762},
{"learn":[0.4222790308],"iteration":652,"passed_time":1.819052546,"remaining_time":0.9666328232},
{"learn":[0.4222568502],"iteration":653,"passed_time":1.821707094,"remaining_time":0.9637777594},
{"learn":[0.4222244452],"iteration":654,"passed_time":1.824440225,"remaining_time":0.9609646985},
{"learn":[0.422170947],"iteration":655,"passed_time":1.827156813,"remaining_time":0.9581432071},
{"learn":[0.4221528387],"iteration":656,"passed_time":1.829795195,"remaining_time":0.9552812053},
{"learn":[0.4221337584],"iteration":657,"passed_time":1.832365994,"remaining_time":0.9523847568},
{"learn":[0.4220939365],"iteration":658,"passed_time":1.835134416,"remaining_time":0.9495915565},
{"learn":[0.4220789161],"iteration":659,"passed_time":1.837881629,"remaining_time":0.9467875059},
{"learn":[0.422046769],"iteration":660,"passed_time":1.840841381,"remaining_time":0.9440926298},
{"learn":[0.4220350999],"iteration":661,"passed_time":1.843371264,"remaining_time":0.9411774734},
{"learn":[0.4220184375],"iteration":662,"passed_time":1.846043021,"remaining_time":0.9383355926},
{"learn":[0.4219828146],"iteration":663,"passed_time":1.848653652,"remaining_time":0.935463294},
{"learn":[0.4219520265],"iteration":664,"passed_time":1.851153869,"remaining_time":0.9325361597},
{"learn":[0.4219419462],"iteration":665,"passed_time":1.853519921,"remaining_time":0.9295430235},
{"learn":[0.4219258742],"iteration":666,"passed_time":1.856090803,"remaining_time":0.9266540293},
{"learn":[0.4219031923],"iteration":667,"passed_time":1.858688561,"remaining_time":0.9237793445},
{"learn":[0.4218800994],"iteration":668,"passed_time":1.862164806,"remaining_time":0.9213401357},
{"learn":[0.4218538814],"iteration":669,"passed_time":1.865051518,"remaining_time":0.9186074639},
{"learn":[0.4218322347],"iteration":670,"passed_time":1.867563776,"remaining_time":0.9156907336},
{"learn":[0.4218081265],"iteration":671,"passed_time":1.869931578,"remaining_time":0.9127046986},
{"learn":[0.4217932724],"iteration":672,"passed_time":1.872426378,"remaining_time":0.9097822073},
{"learn":[0.4217764211],"iteration":673,"passed_time":1.875221257,"remaining_time":0.9070061274},
{"learn":[0.4217658261],"iteration":674,"passed_time":1.878021637,"remaining_time":0.9042326399},
{"learn":[0.4217455487],"iteration":675,"passed_time":1.880481062,"remaining_time":0.9012956571},
{"learn":[0.421724463],"iteration":676,"passed_time":1.882898572,"remaining_time":0.8983400867},
{"learn":[0.4217073674],"iteration":677,"passed_time":1.885581161,"remaining_time":0.8955119969},
{"learn":[0.4216728824],"iteration":678,"passed_time":1.888258875,"remaining_time":0.892682031},
{"learn":[0.4216387725],"iteration":679,"passed_time":1.891190586,"remaining_time":0.8899720407},
{"learn":[0.4216172845],"iteration":680,"passed_time":1.893856218,"remaining_time":0.8871367598},
{"learn":[0.4215924165],"iteration":681,"passed_time":1.896393976,"remaining_time":0.8842423522},
{"learn":[0.4215682007],"iteration":682,"passed_time":1.898897817,"remaining_time":0.8813332475},
{"learn":[0.4215548848],"iteration":683,"passed_time":1.901134579,"remaining_time":0.8783019401},
{"learn":[0.4215281212],"iteration":684,"passed_time":1.903627004,"remaining_time":0.8753905202},
{"learn":[0.4215064812],"iteration":685,"passed_time":1.906018264,"remaining_time":0.872434016},
{"learn":[0.4214724207],"iteration":686,"passed_time":1.90896185,"remaining_time":0.8697307992},
{"learn":[0.421440502],"iteration":687,"passed_time":1.911504816,"remaining_time":0.8668452073},
{"learn":[0.4214135569],"iteration":688,"passed_time":1.914093698,"remaining_time":0.8639813356},
{"learn":[0.421377769],"iteration":689,"passed_time":1.916505416,"remaining_time":0.8610386653},
{"learn":[0.4213316436],"iteration":690,"passed_time":1.918974675,"remaining_time":0.8581232628},
{"learn":[0.4213072482],"iteration":691,"passed_time":1.921620098,"remaining_time":0.8552875582},
{"learn":[0.4212987477],"iteration":692,"passed_time":1.924462144,"remaining_time":0.8525395067},
{"learn":[0.4212652198],"iteration":693,"passed_time":1.927508562,"remaining_time":0.8498812966},
{"learn":[0.4212460732],"iteration":694,"passed_time":1.930051736,"remaining_time":0.8470011216},
{"learn":[0.4212216259],"iteration":695,"passed_time":1.932680618,"remaining_time":0.8441593503},
{"learn":[0.4211801106],"iteration":696,"passed_time":1.93536854,"remaining_time":0.8413438561},
{"learn":[0.4211399471],"iteration":697,"passed_time":1.937773675,"remaining_time":0.8384063751},
{"learn":[0.4211179776],"iteration":698,"passed_time":1.940418723,"remaining_time":0.8355737277},
{"learn":[0.4210932695],"iteration":699,"passed_time":1.943305893,"remaining_time":0.8328453827},
{"learn":[0.4210609351],"iteration":700,"passed_time":1.945991607,"remaining_time":0.830030657},
{"learn":[0.4210347464],"iteration":701,"passed_time":1.948988942,"remaining_time":0.8273485824},
{"learn":[0.4210048402],"iteration":702,"passed_time":1.951593158,"remaining_time":0.8244995275},
{"learn":[0.4209886373],"iteration":703,"passed_time":1.954191873,"remaining_time":0.8216488558},
{"learn":[0.42096922],"iteration":704,"passed_time":1.956556342,"remaining_time":0.8187008806},
{"learn":[0.4209559916],"iteration":705,"passed_time":1.958952852,"remaining_time":0.8157679013},
{"learn":[0.4209320928],"iteration":706,"passed_time":1.961447985,"remaining_time":0.812877312},
{"learn":[0.4209162138],"iteration":707,"passed_time":1.963783787,"remaining_time":0.8099221269},
{"learn":[0.4209038089],"iteration":708,"passed_time":1.966206047,"remaining_time":0.8070041743},
{"learn":[0.4208896063],"iteration":709,"passed_time":1.969043384,"remaining_time":0.8042571568},
{"learn":[0.4208690988],"iteration":710,"passed_time":1.971719015,"remaining_time":0.8014441566},
{"learn":[0.4208517526],"iteration":711,"passed_time":1.974369438,"remaining_time":0.7986213457},
{"learn":[0.4208207719],"iteration":712,"passed_time":1.97697107,"remaining_time":0.7957793788},
{"learn":[0.4208037731],"iteration":713,"passed_time":1.979751325,"remaining_time":0.7930096343},
{"learn":[0.4207734622],"iteration":714,"passed_time":1.982319666,"remaining_time":0.7901553912},
{"learn":[0.4207365879],"iteration":715,"passed_time":1.984656051,"remaining_time":0.7872099421},
{"learn":[0.4207124645],"iteration":716,"passed_time":1.987592095,"remaining_time":0.7845028773},
{"learn":[0.4206889778],"iteration":717,"passed_time":1.990339684,"remaining_time":0.7817211572},
{"learn":[0.4206644946],"iteration":718,"passed_time":1.992738485,"remaining_time":0.7788032189},
{"learn":[0.4206510372],"iteration":719,"passed_time":1.995577198,"remaining_time":0.776057799},
{"learn":[0.4206282127],"iteration":720,"passed_time":1.998028248,"remaining_time":0.7731621099},
{"learn":[0.4206120639],"iteration":721,"passed_time":2.000306718,"remaining_time":0.7702012016},
{"learn":[0.4205965624],"iteration":722,"passed_time":2.002910642,"remaining_time":0.767366871},
{"learn":[0.4205675727],"iteration":723,"passed_time":2.005669063,"remaining_time":0.7645920738},
{"learn":[0.4205527774],"iteration":724,"passed_time":2.008318403,"remaining_time":0.761775946},
{"learn":[0.4205126899],"iteration":725,"passed_time":2.011988188,"remaining_time":0.7593454041},
{"learn":[0.4204870136],"iteration":726,"passed_time":2.014708735,"remaining_time":0.7565549994},
{"learn":[0.4204722631],"iteration":727,"passed_time":2.017394366,"remaining_time":0.753751741},
{"learn":[0.4204421415],"iteration":728,"passed_time":2.020122163,"remaining_time":0.7509644802},
{"learn":[0.4204252936],"iteration":729,"passed_time":2.022866876,"remaining_time":0.7481836391},
{"learn":[0.4204054166],"iteration":730,"passed_time":2.025471216,"remaining_time":0.7453512411},
{"learn":[0.4203908418],"iteration":731,"passed_time":2.028100348,"remaining_time":0.7425285428},
{"learn":[0.4203656966],"iteration":732,"passed_time":2.03135418,"remaining_time":0.7399339236},
{"learn":[0.4203285516],"iteration":733,"passed_time":2.033982312,"remaining_time":0.7371107559},
{"learn":[0.4202917509],"iteration":734,"passed_time":2.036757608,"remaining_time":0.7343411784},
{"learn":[0.4202726291],"iteration":735,"passed_time":2.039586945,"remaining_time":0.7315909695},
{"learn":[0.4202478957],"iteration":736,"passed_time":2.042271701,"remaining_time":0.7287889517},
{"learn":[0.4202210756],"iteration":737,"passed_time":2.044829667,"remaining_time":0.7259422396},
{"learn":[0.4202046958],"iteration":738,"passed_time":2.047487465,"remaining_time":0.7231315675},
{"learn":[0.4201729001],"iteration":739,"passed_time":2.050567633,"remaining_time":0.7204697087},
{"learn":[0.4201639067],"iteration":740,"passed_time":2.053462052,"remaining_time":0.717741797},
{"learn":[0.4201482824],"iteration":741,"passed_time":2.056303015,"remaining_time":0.7149948487},
{"learn":[0.4201185447],"iteration":742,"passed_time":2.058715399,"remaining_time":0.7120994045},
{"learn":[0.4200949318],"iteration":743,"passed_time":2.06101841,"remaining_time":0.709167625},
{"learn":[0.4200776181],"iteration":744,"passed_time":2.063768499,"remaining_time":0.7063905599},
{"learn":[0.4200522939],"iteration":745,"passed_time":2.066611711,"remaining_time":0.7036452742},
{"learn":[0.4200255327],"iteration":746,"passed_time":2.069241051,"remaining_time":0.7008272903},
{"learn":[0.4200110554],"iteration":747,"passed_time":2.071721768,"remaining_time":0.6979597399},
{"learn":[0.4199758047],"iteration":748,"passed_time":2.074043195,"remaining_time":0.6950398424},
{"learn":[0.4199666714],"iteration":749,"passed_time":2.076535537,"remaining_time":0.6921785123},
{"learn":[0.4199459704],"iteration":750,"passed_time":2.079034337,"remaining_time":0.6893203062},
{"learn":[0.4199294423],"iteration":751,"passed_time":2.081544804,"remaining_time":0.6864669033},
{"learn":[0.4199051539],"iteration":752,"passed_time":2.084272476,"remaining_time":0.6836856594},
{"learn":[0.4198967929],"iteration":753,"passed_time":2.086960357,"remaining_time":0.6808915752},
{"learn":[0.4198773298],"iteration":754,"passed_time":2.089653321,"remaining_time":0.678099422},
{"learn":[0.419858734],"iteration":755,"passed_time":2.092175412,"remaining_time":0.6752523817},
{"learn":[0.4198331449],"iteration":756,"passed_time":2.094743045,"remaining_time":0.6724208189},
{"learn":[0.4198218595],"iteration":757,"passed_time":2.097017389,"remaining_time":0.669496317},
{"learn":[0.4198107245],"iteration":758,"passed_time":2.099483982,"remaining_time":0.6666345712},
{"learn":[0.4197850994],"iteration":759,"passed_time":2.102264361,"remaining_time":0.6638729562},
{"learn":[0.4197783008],"iteration":760,"passed_time":2.105235738,"remaining_time":0.6611712766},
{"learn":[0.4197473097],"iteration":761,"passed_time":2.107907703,"remaining_time":0.6583753718},
{"learn":[0.419724667],"iteration":762,"passed_time":2.110877122,"remaining_time":0.6556721859},
{"learn":[0.4196998348],"iteration":763,"passed_time":2.113084092,"remaining_time":0.6527327825},
{"learn":[0.419683606],"iteration":764,"passed_time":2.115443269,"remaining_time":0.64984205},
{"learn":[0.4196495997],"iteration":765,"passed_time":2.118001902,"remaining_time":0.6470136358},
{"learn":[0.4196344459],"iteration":766,"passed_time":2.120362079,"remaining_time":0.644125638},
{"learn":[0.4196184192],"iteration":767,"passed_time":2.123166,"remaining_time":0.6413730625},
{"learn":[0.4196098675],"iteration":768,"passed_time":2.125810881,"remaining_time":0.6385725794},
{"learn":[0.4195927297],"iteration":769,"passed_time":2.12839843,"remaining_time":0.6357553753},
{"learn":[0.4195781339],"iteration":770,"passed_time":2.131436223,"remaining_time":0.6330724969},
{"learn":[0.419561017],"iteration":771,"passed_time":2.133841816,"remaining_time":0.6302019872},
{"learn":[0.4195375115],"iteration":772,"passed_time":2.136491156,"remaining_time":0.6274042592},
{"learn":[0.4194982326],"iteration":773,"passed_time":2.139230244,"remaining_time":0.6246331205},
{"learn":[0.4194689957],"iteration":774,"passed_time":2.142154622,"remaining_time":0.6219158581},
{"learn":[0.4194583874],"iteration":775,"passed_time":2.144776004,"remaining_time":0.6191105991},
{"learn":[0.4194251076],"iteration":776,"passed_time":2.147637424,"remaining_time":0.6163747048},
{"learn":[0.4194108755],"iteration":777,"passed_time":2.151020963,"remaining_time":0.6137874726},
{"learn":[0.4193899725],"iteration":778,"passed_time":2.153670511,"remaining_time":0.6109899652},
{"learn":[0.4193545932],"iteration":779,"passed_time":2.156461099,"remaining_time":0.6082326175},
{"learn":[0.4193208532],"iteration":780,"passed_time":2.159237562,"remaining_time":0.6054712241},
{"learn":[0.4193045376],"iteration":781,"passed_time":2.162171481,"remaining_time":0.6027536865},
{"learn":[0.419285205],"iteration":782,"passed_time":2.164592949,"remaining_time":0.5998935758},
{"learn":[0.4192709194],"iteration":783,"passed_time":2.167052833,"remaining_time":0.5970451682},
{"learn":[0.4192328507],"iteration":784,"passed_time":2.169752755,"remaining_time":0.5942634934},
{"learn":[0.4192122807],"iteration":785,"passed_time":2.172428511,"remaining_time":0.591475447},
{"learn":[0.4191830773],"iteration":786,"passed_time":2.174974227,"remaining_time":0.588652491},
{"learn":[0.4191543186],"iteration":787,"passed_time":2.177949104,"remaining_time":0.5859456981},
{"learn":[0.419131126],"iteration":788,"passed_time":2.180484821,"remaining_time":0.5831207822},
{"learn":[0.4191083351],"iteration":789,"passed_time":2.183077869,"remaining_time":0.5803118387},
{"learn":[0.4190775145],"iteration":790,"passed_time":2.185553211,"remaining_time":0.5774723403},
{"learn":[0.4190425042],"iteration":791,"passed_time":2.188191593,"remaining_time":0.57467658},
{"learn":[0.4190237068],"iteration":792,"passed_time":2.19095764,"remaining_time":0.5719145415},
{"learn":[0.4190092388],"iteration":793,"passed_time":2.19342594,"remaining_time":0.5690752439},
{"learn":[0.4189907316],"iteration":794,"passed_time":2.195863033,"remaining_time":0.5662288323},
{"learn":[0.4189753349],"iteration":795,"passed_time":2.198588955,"remaining_time":0.5634574708},
{"learn":[0.4189515765],"iteration":796,"passed_time":2.202127866,"remaining_time":0.5608932958},
{"learn":[0.4189357888],"iteration":797,"passed_time":2.204623541,"remaining_time":0.5580626006},
{"learn":[0.4189108461],"iteration":798,"passed_time":2.208203368,"remaining_time":0.5555054782},
{"learn":[0.4188958165],"iteration":799,"passed_time":2.210882499,"remaining_time":0.5527206249},
{"learn":[0.41887206],"iteration":800,"passed_time":2.213852252,"remaining_time":0.5500082373},
{"learn":[0.4188419971],"iteration":801,"passed_time":2.216799629,"remaining_time":0.547289684},
{"learn":[0.4188132058],"iteration":802,"passed_time":2.219807589,"remaining_time":0.5445854235},
{"learn":[0.4187902533],"iteration":803,"passed_time":2.22297688,"remaining_time":0.541919737},
{"learn":[0.4187759017],"iteration":804,"passed_time":2.22575376,"remaining_time":0.5391577431},
{"learn":[0.4187588404],"iteration":805,"passed_time":2.22888776,"remaining_time":0.5364816692},
{"learn":[0.4187402374],"iteration":806,"passed_time":2.231819888,"remaining_time":0.5337561813},
{"learn":[0.4187083604],"iteration":807,"passed_time":2.234658766,"remaining_time":0.5310080237},
{"learn":[0.4186918813],"iteration":808,"passed_time":2.237236524,"remaining_time":0.5281979926},
{"learn":[0.4186584335],"iteration":809,"passed_time":2.23999832,"remaining_time":0.5254317048},
{"learn":[0.4186378566],"iteration":810,"passed_time":2.243316735,"remaining_time":0.5227951453},
{"learn":[0.4186178047],"iteration":811,"passed_time":2.24613878,"remaining_time":0.5200419836},
{"learn":[0.4186005816],"iteration":812,"passed_time":2.249440236,"remaining_time":0.5173989228},
{"learn":[0.4185609707],"iteration":813,"passed_time":2.252051285,"remaining_time":0.5145964853},
{"learn":[0.418538319],"iteration":814,"passed_time":2.255246034,"remaining_time":0.5119270139},
{"learn":[0.4185109834],"iteration":815,"passed_time":2.257650002,"remaining_time":0.5090779417},
{"learn":[0.4185048431],"iteration":816,"passed_time":2.260383757,"remaining_time":0.5063038282},
{"learn":[0.4184904027],"iteration":817,"passed_time":2.263240844,"remaining_time":0.5035572539},
{"learn":[0.4184713831],"iteration":818,"passed_time":2.265908976,"remaining_time":0.5007686503},
{"learn":[0.4184500032],"iteration":819,"passed_time":2.268672814,"remaining_time":0.4980013494},
{"learn":[0.4184369867],"iteration":820,"passed_time":2.271132156,"remaining_time":0.4951676686},
{"learn":[0.4184213861],"iteration":821,"passed_time":2.273483333,"remaining_time":0.492311476},
{"learn":[0.4184064745],"iteration":822,"passed_time":2.276408878,"remaining_time":0.4895800381},
{"learn":[0.4183855706],"iteration":823,"passed_time":2.278769763,"remaining_time":0.4867275222},
{"learn":[0.4183536397],"iteration":824,"passed_time":2.281200647,"remaining_time":0.4838910464},
{"learn":[0.4183365686],"iteration":825,"passed_time":2.283911069,"remaining_time":0.4811144383},
{"learn":[0.4183232232],"iteration":826,"passed_time":2.287300816,"remaining_time":0.4784800981},
{"learn":[0.4182923674],"iteration":827,"passed_time":2.289835991,"remaining_time":0.4756664135},
{"learn":[0.4182619492],"iteration":828,"passed_time":2.292044836,"remaining_time":0.472786088},
{"learn":[0.4182470603],"iteration":829,"passed_time":2.294856715,"remaining_time":0.4700308935},
{"learn":[0.4182404438],"iteration":830,"passed_time":2.298412001,"remaining_time":0.4674267488},
{"learn":[0.418224329],"iteration":831,"passed_time":2.302097494,"remaining_time":0.4648466094},
{"learn":[0.4182183402],"iteration":832,"passed_time":2.304895874,"remaining_time":0.4620859674},
{"learn":[0.4181852278],"iteration":833,"passed_time":2.308120747,"remaining_time":0.4594101248},
{"learn":[0.4181685077],"iteration":834,"passed_time":2.310702005,"remaining_time":0.4566057853},
{"learn":[0.4181440478],"iteration":835,"passed_time":2.313463593,"remaining_time":0.4538373555},
{"learn":[0.4181151228],"iteration":836,"passed_time":2.316175723,"remaining_time":0.4510593105},
{"learn":[0.4181012841],"iteration":837,"passed_time":2.318875563,"remaining_time":0.4482790467},
{"learn":[0.4180889556],"iteration":838,"passed_time":2.321425904,"remaining_time":0.4454702866},
{"learn":[0.418066137],"iteration":839,"passed_time":2.324161159,"remaining_time":0.4426973636},
{"learn":[0.4180441433],"iteration":840,"passed_time":2.327041746,"remaining_time":0.4399520066},
{"learn":[0.4180242356],"iteration":841,"passed_time":2.330577407,"remaining_time":0.4373292521},
{"learn":[0.4180111036],"iteration":842,"passed_time":2.333340662,"remaining_time":0.4345604791},
{"learn":[0.417994658],"iteration":843,"passed_time":2.336077417,"remaining_time":0.4317868211},
{"learn":[0.4179784091],"iteration":844,"passed_time":2.338164889,"remaining_time":0.4288941513},
{"learn":[0.4179598393],"iteration":845,"passed_time":2.340885311,"remaining_time":0.4261186028},
{"learn":[0.4179471283],"iteration":846,"passed_time":2.343821064,"remaining_time":0.4233820812},
{"learn":[0.4179306081],"iteration":847,"passed_time":2.347308309,"remaining_time":0.4207439422},
{"learn":[0.4179126204],"iteration":848,"passed_time":2.350416143,"remaining_time":0.4180363222},
{"learn":[0.4179034275],"iteration":849,"passed_time":2.353334354,"remaining_time":0.4152942978},
{"learn":[0.4178762411],"iteration":850,"passed_time":2.355831987,"remaining_time":0.4124782211},
{"learn":[0.4178579514],"iteration":851,"passed_time":2.358786115,"remaining_time":0.409742189},
{"learn":[0.4178266935],"iteration":852,"passed_time":2.362003072,"remaining_time":0.4070509397},
{"learn":[0.4177917226],"iteration":853,"passed_time":2.364552163,"remaining_time":0.4042442808},
{"learn":[0.4177628534],"iteration":854,"passed_time":2.367075671,"remaining_time":0.4014338858},
{"learn":[0.4177481467],"iteration":855,"passed_time":2.369991841,"remaining_time":0.3986902162},
{"learn":[0.4177281247],"iteration":856,"passed_time":2.372515557,"remaining_time":0.3958806589},
{"learn":[0.4177152323],"iteration":857,"passed_time":2.375133064,"remaining_time":0.3930872903},
{"learn":[0.4177037328],"iteration":858,"passed_time":2.37779757,"remaining_time":0.3903020459},
{"learn":[0.4176831023],"iteration":859,"passed_time":2.380384119,"remaining_time":0.3875043915},
{"learn":[0.4176631856],"iteration":860,"passed_time":2.38322854,"remaining_time":0.3847488583},
{"learn":[0.417643471],"iteration":861,"passed_time":2.386083252,"remaining_time":0.3819947665},
{"learn":[0.4176181793],"iteration":862,"passed_time":2.388627634,"remaining_time":0.3791911772},
{"learn":[0.4175981105],"iteration":863,"passed_time":2.39106756,"remaining_time":0.3763717456},
{"learn":[0.417578875],"iteration":864,"passed_time":2.393677317,"remaining_time":0.3735796969},
{"learn":[0.4175455407],"iteration":865,"passed_time":2.396543362,"remaining_time":0.3708277258},
{"learn":[0.4175221409],"iteration":866,"passed_time":2.399225118,"remaining_time":0.3680472212},
{"learn":[0.417504524],"iteration":867,"passed_time":2.401926457,"remaining_time":0.3652699221},
{"learn":[0.417487365],"iteration":868,"passed_time":2.404449341,"remaining_time":0.362465896},
{"learn":[0.4174720356],"iteration":869,"passed_time":2.407477259,"remaining_time":0.3597379812},
{"learn":[0.4174379082],"iteration":870,"passed_time":2.410022808,"remaining_time":0.356937936},
{"learn":[0.4174212069],"iteration":871,"passed_time":2.412726522,"remaining_time":0.3541616913},
{"learn":[0.4174093671],"iteration":872,"passed_time":2.415455486,"remaining_time":0.351389286},
{"learn":[0.4173832512],"iteration":873,"passed_time":2.41815595,"remaining_time":0.3486128715},
{"learn":[0.4173516031],"iteration":874,"passed_time":2.420348754,"remaining_time":0.3457641077},
{"learn":[0.4173236009],"iteration":875,"passed_time":2.422782638,"remaining_time":0.3429509671},
{"learn":[0.41730627],"iteration":876,"passed_time":2.425461478,"remaining_time":0.3401730465},
{"learn":[0.41728384],"iteration":877,"passed_time":2.428611352,"remaining_time":0.337460803},
{"learn":[0.4172696624],"iteration":878,"passed_time":2.431593604,"remaining_time":0.3347244893},
{"learn":[0.4172526107],"iteration":879,"passed_time":2.434677188,"remaining_time":0.3320014348},
{"learn":[0.4172347896],"iteration":880,"passed_time":2.437486318,"remaining_time":0.3292404901},
{"learn":[0.4172087037],"iteration":881,"passed_time":2.440119158,"remaining_time":0.326455851},
{"learn":[0.4171925827],"iteration":882,"passed_time":2.442883662,"remaining_time":0.3236890017},
{"learn":[0.4171634581],"iteration":883,"passed_time":2.445568043,"remaining_time":0.3209116437},
{"learn":[0.4171390012],"iteration":884,"passed_time":2.447965928,"remaining_time":0.3180972675},
{"learn":[0.4171104793],"iteration":885,"passed_time":2.450634351,"remaining_time":0.3153186411},
{"learn":[0.4170869028],"iteration":886,"passed_time":2.453882849,"remaining_time":0.3126141623},
{"learn":[0.4170692532],"iteration":887,"passed_time":2.456115736,"remaining_time":0.3097803632},
{"learn":[0.4170369037],"iteration":888,"passed_time":2.459084739,"remaining_time":0.3070398268},
{"learn":[0.4170105348],"iteration":889,"passed_time":2.461601663,"remaining_time":0.3042429022},
{"learn":[0.4169871465],"iteration":890,"passed_time":2.464060464,"remaining_time":0.3014394956},
{"learn":[0.4169680383],"iteration":891,"passed_time":2.466738137,"remaining_time":0.2986633618},
{"learn":[0.4169391864],"iteration":892,"passed_time":2.469187188,"remaining_time":0.2958600549},
{"learn":[0.4169182716],"iteration":893,"passed_time":2.472525935,"remaining_time":0.2931630303},
{"learn":[0.4168935622],"iteration":894,"passed_time":2.475242982,"remaining_time":0.2903916348},
{"learn":[0.4168840251],"iteration":895,"passed_time":2.477786156,"remaining_time":0.2876001789},
{"learn":[0.4168646456],"iteration":896,"passed_time":2.4807822,"remaining_time":0.2848612782},
{"learn":[0.4168370522],"iteration":897,"passed_time":2.483455581,"remaining_time":0.2820851551},
{"learn":[0.4168189359],"iteration":898,"passed_time":2.485991256,"remaining_time":0.2792937896},
{"learn":[0.4167982347],"iteration":899,"passed_time":2.488799218,"remaining_time":0.2765332465},
{"learn":[0.4167821627],"iteration":900,"passed_time":2.491758679,"remaining_time":0.2737892444},
{"learn":[0.4167579376],"iteration":901,"passed_time":2.49503476,"remaining_time":0.2710791646},
{"learn":[0.4167477839],"iteration":902,"passed_time":2.497523852,"remaining_time":0.2682832931},
{"learn":[0.4167351187],"iteration":903,"passed_time":2.499911779,"remaining_time":0.265477357},
{"learn":[0.4167000846],"iteration":904,"passed_time":2.502534619,"remaining_time":0.2626970042},
{"learn":[0.4166844165],"iteration":905,"passed_time":2.505148376,"remaining_time":0.2599160566},
{"learn":[0.4166592172],"iteration":906,"passed_time":2.507744549,"remaining_time":0.2571336749},
{"learn":[0.4166310486],"iteration":907,"passed_time":2.510712427,"remaining_time":0.2543893648},
{"learn":[0.4165995588],"iteration":908,"passed_time":2.51357143,"remaining_time":0.2516336635},
{"learn":[0.41658179],"iteration":909,"passed_time":2.51619902,"remaining_time":0.2488548482},
{"learn":[0.4165569974],"iteration":910,"passed_time":2.519778389,"remaining_time":0.2461693487},
{"learn":[0.4165477783],"iteration":911,"passed_time":2.522475062,"remaining_time":0.2433967165},
{"learn":[0.4165233263],"iteration":912,"passed_time":2.525302941,"remaining_time":0.2406367534},
{"learn":[0.4164881818],"iteration":913,"passed_time":2.52788349,"remaining_time":0.2378533699},
{"learn":[0.4164679949],"iteration":914,"passed_time":2.530333541,"remaining_time":0.235058307},
{"learn":[0.4164542556],"iteration":915,"passed_time":2.532870757,"remaining_time":0.2322719908},
{"learn":[0.4164422256],"iteration":916,"passed_time":2.535642512,"remaining_time":0.2295074465},
{"learn":[0.416410638],"iteration":917,"passed_time":2.538112812,"remaining_time":0.2267159592},
{"learn":[0.4163984949],"iteration":918,"passed_time":2.54054253,"remaining_time":0.223921594},
{"learn":[0.4163597989],"iteration":919,"passed_time":2.543250744,"remaining_time":0.2211522386},
{"learn":[0.4163432953],"iteration":920,"passed_time":2.545582671,"remaining_time":0.2183507394},
{"learn":[0.4163193472],"iteration":921,"passed_time":2.548852669,"remaining_time":0.2156296184},
{"learn":[0.4162909363],"iteration":922,"passed_time":2.551215471,"remaining_time":0.2128316265},
{"learn":[0.4162781349],"iteration":923,"passed_time":2.553739937,"remaining_time":0.2100478736},
{"learn":[0.4162606535],"iteration":924,"passed_time":2.556337653,"remaining_time":0.2072706205},
{"learn":[0.4162440878],"iteration":925,"passed_time":2.558721038,"remaining_time":0.2044766272},
{"learn":[0.4162317618],"iteration":926,"passed_time":2.561387586,"remaining_time":0.2017058185},
{"learn":[0.4162004671],"iteration":927,"passed_time":2.564174924,"remaining_time":0.1989446061},
{"learn":[0.4161821801],"iteration":928,"passed_time":2.567067677,"remaining_time":0.196191394},
{"learn":[0.4161419186],"iteration":929,"passed_time":2.569937514,"remaining_time":0.1934361569},
{"learn":[0.41610992],"iteration":930,"passed_time":2.572552021,"remaining_time":0.1906617502},
{"learn":[0.4160976236],"iteration":931,"passed_time":2.575503815,"remaining_time":0.1879122955},
{"learn":[0.416078856],"iteration":932,"passed_time":2.578127655,"remaining_time":0.1851388562},
{"learn":[0.4160544873],"iteration":933,"passed_time":2.580745536,"remaining_time":0.1823653163},
{"learn":[0.4160265463],"iteration":934,"passed_time":2.58359479,"remaining_time":0.179608194},
{"learn":[0.4160213846],"iteration":935,"passed_time":2.586702457,"remaining_time":0.1768685441},
{"learn":[0.4160047711],"iteration":936,"passed_time":2.589163841,"remaining_time":0.1740846553},
{"learn":[0.4159983815],"iteration":937,"passed_time":2.591797514,"remaining_time":0.1713128421},
{"learn":[0.4159920076],"iteration":938,"passed_time":2.594456062,"remaining_time":0.1685429391},
{"learn":[0.4159830252],"iteration":939,"passed_time":2.597061278,"remaining_time":0.1657698688},
{"learn":[0.4159623166],"iteration":940,"passed_time":2.599654327,"remaining_time":0.1629963924},
{"learn":[0.4159482723],"iteration":941,"passed_time":2.602339707,"remaining_time":0.1602289841},
{"learn":[0.4159244572],"iteration":942,"passed_time":2.604970381,"remaining_time":0.157458443},
{"learn":[0.4159078805],"iteration":943,"passed_time":2.60764472,"remaining_time":0.1546907885},
{"learn":[0.4158749791],"iteration":944,"passed_time":2.610414225,"remaining_time":0.1519288702},
{"learn":[0.4158641642],"iteration":945,"passed_time":2.612846359,"remaining_time":0.149147678},
{"learn":[0.4158557254],"iteration":946,"passed_time":2.615398367,"remaining_time":0.1463739318},
{"learn":[0.4158374245],"iteration":947,"passed_time":2.617989291,"remaining_time":0.1436027881},
{"learn":[0.4158155671],"iteration":948,"passed_time":2.62058159,"remaining_time":0.1408320981},
{"learn":[0.415789818],"iteration":949,"passed_time":2.623957128,"remaining_time":0.1381030067},
{"learn":[0.4157543856],"iteration":950,"passed_time":2.626696633,"remaining_time":0.1353397845},
{"learn":[0.4157285601],"iteration":951,"passed_time":2.629464097,"remaining_time":0.1325780217},
{"learn":[0.4157167704],"iteration":952,"passed_time":2.631734483,"remaining_time":0.1297917321},
{"learn":[0.4156958933],"iteration":953,"passed_time":2.634526196,"remaining_time":0.1270316614},
{"learn":[0.4156693813],"iteration":954,"passed_time":2.637414074,"remaining_time":0.1242760558},
{"learn":[0.4156547565],"iteration":955,"passed_time":2.640222162,"remaining_time":0.1215165012},
{"learn":[0.415625886],"iteration":956,"passed_time":2.642674546,"remaining_time":0.1187408626},
{"learn":[0.4156015595],"iteration":957,"passed_time":2.645312261,"remaining_time":0.115974024},
{"learn":[0.4155926927],"iteration":958,"passed_time":2.648262638,"remaining_time":0.1132208219},
{"learn":[0.4155619597],"iteration":959,"passed_time":2.652154711,"remaining_time":0.1105064463},
{"learn":[0.415538483],"iteration":960,"passed_time":2.655154546,"remaining_time":0.1077534103},
{"learn":[0.4155292593],"iteration":961,"passed_time":2.657880927,"remaining_time":0.1049890595},
{"learn":[0.4155101149],"iteration":962,"passed_time":2.660719847,"remaining_time":0.1022291115},
{"learn":[0.4154811522],"iteration":963,"passed_time":2.663264272,"remaining_time":0.09945800185},
{"learn":[0.415467449],"iteration":964,"passed_time":2.665733656,"remaining_time":0.09668464036},
{"learn":[0.4154483926],"iteration":965,"passed_time":2.668589118,"remaining_time":0.0939254969},
{"learn":[0.4154239716],"iteration":966,"passed_time":2.671210791,"remaining_time":0.09115817591},
{"learn":[0.4154064211],"iteration":967,"passed_time":2.67392663,"remaining_time":0.08839426876},
{"learn":[0.4153867924],"iteration":968,"passed_time":2.676679885,"remaining_time":0.08563165783},
{"learn":[0.4153652012],"iteration":969,"passed_time":2.679195602,"remaining_time":0.08286171964},
{"learn":[0.4153511471],"iteration":970,"passed_time":2.682329435,"remaining_time":0.08011076582},
{"learn":[0.4153368645],"iteration":971,"passed_time":2.685096856,"remaining_time":0.07734846911},
{"learn":[0.4153247835],"iteration":972,"passed_time":2.687957485,"remaining_time":0.0745887483},
{"learn":[0.4153066487],"iteration":973,"passed_time":2.69080053,"remaining_time":0.07182835092},
{"learn":[0.4152704873],"iteration":974,"passed_time":2.693402996,"remaining_time":0.06906161528},
{"learn":[0.4152473201],"iteration":975,"passed_time":2.695930587,"remaining_time":0.0662933751},
{"learn":[0.4152274221],"iteration":976,"passed_time":2.698620218,"remaining_time":0.06352944219},
{"learn":[0.4152032755],"iteration":977,"passed_time":2.701150059,"remaining_time":0.06076206678},
{"learn":[0.4151951412],"iteration":978,"passed_time":2.704089062,"remaining_time":0.05800395332},
{"learn":[0.4151682106],"iteration":979,"passed_time":2.70708848,"remaining_time":0.05524670368},
{"learn":[0.4151559223],"iteration":980,"passed_time":2.709714862,"remaining_time":0.05248173535},
{"learn":[0.4151422502],"iteration":981,"passed_time":2.71201029,"remaining_time":0.04971098291},
{"learn":[0.4151278778],"iteration":982,"passed_time":2.714416925,"remaining_time":0.04694312077},
{"learn":[0.4151150173],"iteration":983,"passed_time":2.716964099,"remaining_time":0.04417827803},
{"learn":[0.4151033788],"iteration":984,"passed_time":2.719542565,"remaining_time":0.04141435378},
{"learn":[0.4150895268],"iteration":985,"passed_time":2.722725147,"remaining_time":0.03865938343},
{"learn":[0.4150674057],"iteration":986,"passed_time":2.725292613,"remaining_time":0.03589544475},
{"learn":[0.415048858],"iteration":987,"passed_time":2.727518417,"remaining_time":0.03312775405},
{"learn":[0.4150172701],"iteration":988,"passed_time":2.730062508,"remaining_time":0.03036469928},
{"learn":[0.4150029327],"iteration":989,"passed_time":2.732363769,"remaining_time":0.02759963403},
{"learn":[0.4149926022],"iteration":990,"passed_time":2.734881319,"remaining_time":0.02483746909},
{"learn":[0.4149780978],"iteration":991,"passed_time":2.737348328,"remaining_time":0.02207538974},
{"learn":[0.4149607152],"iteration":992,"passed_time":2.740035292,"remaining_time":0.01931545523},
{"learn":[0.4149510155],"iteration":993,"passed_time":2.742267887,"remaining_time":0.01655292487},
{"learn":[0.4149416242],"iteration":994,"passed_time":2.744915602,"remaining_time":0.01379354574},
{"learn":[0.4149136806],"iteration":995,"passed_time":2.747446402,"remaining_time":0.01103392129},
{"learn":[0.4148934697],"iteration":996,"passed_time":2.749838203,"remaining_time":0.008274337623},
{"learn":[0.4148799605],"iteration":997,"passed_time":2.752044299,"remaining_time":0.005515118835},
{"learn":[0.4148505554],"iteration":998,"passed_time":2.754538057,"remaining_time":0.002757295353},
{"learn":[0.4148262653],"iteration":999,"passed_time":2.757223272,"remaining_time":0}
]}